Workbook

Sheet Cover
B9: REL FINANCE
B10: RELiable capital. RELationship focused. RELentless in execution.
B13: BRIDGE LOAN BASE MODEL
B14: Whole-loan origination · senior funding · REL junior returns
B17: DEAL
B18: Deal Name | C18: =Inputs!C6 -> Housing First Group
B19: Address | C19: =Inputs!C7 -> TBC
B20: Asset Class / Loan Type | C20: =Inputs!C8&" | "&Inputs!C9 -> Residential | Bridge
B21: Gross Loan | C21: =Inputs!C14 -> 3700000
B22: Term | C22: =TEXT(Inputs!C11,"0")&" months from "&TEXT(Inputs!C10,"dd-mmm-yy") -> 24 months from 01-Aug-26
B25: HEADLINE RETURNS
B26: REL Net Profit | C26: ='Summary & Breakeven'!C9 -> 324111.13
B27: REL IRR | C27: ='Summary & Breakeven'!C10 -> 0.18881354
B28: REL Equity Multiple | C28: ='Summary & Breakeven'!C11 -> 1.3593748
B29: Day-1 LTV / 180-Day LTV | C29: =TEXT('Summary & Breakeven'!C33,"0.0%")&" / "&TEXT('Summary & Breakeven'!C35,"0.0%") -> 59.9% / 85.8%
B32: HOW TO USE
B33: Blue cells on the Inputs sheet are the only cells to change. All calculations, the monthly cashflow
B34: ledger, the fee breakdown and the summary & breakeven metrics flow through automatically.
B35: Interest is actual/365, monthly periods via EDATE. Model supports terms up to 36 months.
B36: Every fee is a line item in the ledger: arrangement, broker and admin fees and any interest
B37: reserve appear as day-1 rows; the exit fee and principal redemption are separate rows at maturity.
B38: A mid-term rate change (base rate reset) can be modelled with the New Rate inputs.
B39: Cashflow columns B:H are the borrower-facing ledger – copy and paste directly for brokers.
B40: The Statement tab turns the model into a borrower statement in the REL statement format:
B41: set the Statement Date and #, then print / PDF the tab. Rows flag Complete or Forecast.
B42: Save a renamed copy per deal, e.g. [DealName]_Financial_Model.xlsx.
B45: REL Finance Limited
... B48: Internal underwriting model – for information purposes only; does not constitute investment advice.

Sheet Inputs
B2: REL FINANCE – BRIDGE LOAN BASE MODEL
B3: Blue cells = inputs. Black cells = calculated. Change inputs only.
B5: DEAL INFORMATION
B6: Deal Name | C6: Housing First Group
B7: Address | C7: TBC
B8: Asset Class | C8: Residential | E8: Dropdown – drives which breakeven metrics apply
B9: Loan Type | C9: Bridge | E9: Dropdown
B10: Drawdown Date | C10: 46235
B11: Term (months) | C11: 24 | E11: Change term here – cashflow flexes automatically (max 36)
B13: WHOLE LOAN TERMS (borrower facing) | D13: £ amount
B14: Gross Loan (£) | C14: 3700000
B15: Arrangement Fee % | C15: 0.01 | D15: =C14*C15 -> 37000 | E15: REL income, deducted from advance on day 1
B16: Broker Fee % | C16: 0 | D16: =C14*C16 -> 0 | E16: Paid away to broker – reduces borrower net advance only, not REL income
B17: Exit Fee % | C17: 0.01 | D17: =C14*C17 -> 37000 | E17: On gross loan, payable at redemption – REL income
B18: Admin / Other Fee (£) | C18: 0 | E18: Flat fee deducted on day 1 – REL income (0 if none)
B19: Margin % | C19: 0.045
B20: Base Rate % | C20: 0.0375
B21: Total Interest Rate | C21: =C19+C20 -> 0.0825 | E21: Margin + base
B22: New Rate % (optional) | E22: Leave blank unless the rate changes mid-term (e.g. base rate reset)
B23: New Rate Effective From | E23: Date the new rate applies from – leave blank if no change
B24: Interest Treatment | C24: Serviced Monthly | E24: Dropdown – Serviced Monthly or Retained (Reserve)
B25: Interest Reserve (£) | C25: =IF(C24="Retained (Reserve)",C14*C21*C11/12,0) -> 0 | E25: Gross × headline rate × term/12 if retained – review if using a rate change
B26: Day-1 Net Advance to Borrower | C26: =C14-D15-D16-C18-C25 -> 3663000 | E26: Gross less arrangement, broker & admin fees and reserve
B28: FUNDING STRUCTURE (how REL funds the loan)
B29: Structure | C29: Senior Funder + REL Junior | E29: Dropdown – set to Unlevered (REL 100%) if REL funds the whole loan
B30: Senior Funder | C30: GB Bank
B31: Senior Loan (£) | C31: 2775000 | E31: Amount raised from senior funder
B32: Senior Arrangement Fee % | C32: 0.005 | D32: =C37*C32 -> 13875 | E32: Cost to REL, paid day 1
B33: Senior Margin % | C33: 0.025
B34: Senior Base Rate % | C34: 0.0375
B35: Senior Total Rate | C35: =C33+C34 -> 0.0625
B36: Senior Exit Fee % | C36: 0 | D36: =C37*C36 -> 0 | E36: Cost to REL at redemption
B37: Effective Senior Loan | C37: =IF(C29="Unlevered (REL 100%)",0,MIN(C31,C14)) -> 2775000 | E37: Zero if unlevered
B38: REL Net Capital (junior piece) | C38: =C14-C37 -> 925000 | E38: REL money in the deal
B40: ASSET METRICS
B41: Market Value (£) | C41: 6175000
B42: 180-Day / Restricted MV (£) | C42: 4355000
B43: Purchase Price (£) | C43: 4200000 | E43: Leave blank if refinance
B44: Area (sq ft) | E44: For breakeven £psf
B45: No. of Units | C45: 16 | E45: For breakeven per unit (resi blocks)
B46: No. of Beds / Rooms | C46: 0 | E46: For breakeven per bed (hotels)
B47: Annual Rent / EBITDA (£) | C47: 461452 | E47: For debt yield (income-producing assets)

Sheet Cashflow
B1: MONTHLY CASHFLOW LEDGER – ACT/365
B2: =Inputs!C6&" | "&Inputs!C8&" | Term: "&Inputs!C11&" months" -> Housing First Group | Residential | Term: 24 months
B4: WHOLE LOAN – BORROWER LEDGER (copy B:H for broker) | I4: REL VIEW | K4: SENIOR FUNDING (REL as borrower from senior) | R4: REL FINANCE – NET POSITION | Z4: CALC ENGINE – feeds IRRs (do not edit)
A5: Mo | B5: Date | C5: Details | D5: Days | E5: Paid Out (£) | F5: Interest (£) | G5: Paid In (£) | H5: Loan Balance (£) | I5: Net CF (£) | K5: Details | L5: Paid Out (£) | M5: Interest (£) | N5: Paid In (£) | O5: Balance (£) | P5: Net CF (£) | R5: Details | S5: Paid Out (£) | T5: Net Interest (£) | U5: Paid In (£) | V5: REL Capital (£) | W5: Net CF (£) | X5: Days @ new | Z5: Date | AA5: Whole CF (£) | AB5: REL CF (£)
A6: 0 | B6: =Inputs!$C$10 -> 46235 | C6: Drawdown – gross loan advanced | E6: =Inputs!$C$14 -> 3700000 | F6: 0 | G6: 0 | H6: =Inputs!$C$14 -> 3700000 | I6: =-Inputs!$C$14 -> -3700000 | K6: ="Senior drawdown from "&Inputs!$C$30 -> Senior drawdown from GB Bank | L6: 0 | M6: 0 | N6: =Inputs!$C$37 -> 2775000 | O6: =Inputs!$C$37 -> 2775000 | P6: =N6-L6 -> 2775000 | R6: Fund whole loan / draw senior | S6: =Inputs!$C$14 -> 3700000 | T6: 0 | U6: =Inputs!$C$37 -> 2775000 | V6: =Inputs!$C$38 -> 925000 | W6: =U6-S6 -> -925000 | Z6: =EDATE(Inputs!$C$10,0) -> 46235 | AA6: =-(Inputs!$C$14-Inputs!$D$15-Inputs!$C$18-Inputs!$C$25) -> -3663000 | AB6: =AA6+Inputs!$C$37-Inputs!$D$32 -> -901875
B7: =Inputs!$C$10 -> 46235 | C7: ="Arrangement fee ("&TEXT(Inputs!$C$15,"0.00%")&") – deducted at source" -> Arrangement fee (1.00%) – deducted at source | E7: 0 | F7: 0 | G7: =Inputs!$D$15 -> 37000 | H7: =Inputs!$C$14 -> 3700000 | I7: =Inputs!$D$15 -> 37000 | K7: =IF(Inputs!$C$37=0,"","Senior arrangement fee ("&TEXT(Inputs!$C$32,"0.00%")&")") -> Senior arrangement fee (0.50%) | L7: =Inputs!$D$32 -> 13875 | M7: 0 | N7: 0 | O7: =Inputs!$C$37 -> 2775000 | P7: =N7-L7 -> -13875 | R7: Arrangement fees: earned less senior AF paid | S7: =Inputs!$D$32 -> 13875 | T7: 0 | U7: =Inputs!$D$15 -> 37000 | V7: =Inputs!$C$38 -> 925000 | W7: =U7-S7 -> 23125 | Z7: =EDATE(Inputs!$C$10,1) -> 46266 | AA7: =IF(1<=Inputs!$C$11,IF(Inputs!$C$24="Serviced Monthly",F11,0)+IF(1=Inputs!$C$11,Inputs!$C$14+Inputs!$D$17,0),0) -> 25925.342 | AB7: =AA7-IF(1<=Inputs!$C$11,M11,0)-IF(1=Inputs!$C$11,Inputs!$C$37+Inputs!$D$36,0) -> 11195.034
B8: =Inputs!$C$10 -> 46235 | C8: ="Broker fee ("&TEXT(Inputs!$C$16,"0.00%")&") – paid away to broker" -> Broker fee (0.00%) – paid away to broker | E8: 0 | F8: 0 | G8: =Inputs!$D$16 -> 0 | H8: =Inputs!$C$14 -> 3700000 | I8: 0 | L8: 0 | M8: 0 | N8: 0 | O8: =Inputs!$C$37 -> 2775000 | P8: =N8-L8 -> 0 | R8: Broker fee – collected and paid away (nil to REL) | S8: =Inputs!$D$16 -> 0 | T8: 0 | U8: =Inputs!$D$16 -> 0 | V8: =Inputs!$C$38 -> 925000 | W8: =U8-S8 -> 0 | Z8: =EDATE(Inputs!$C$10,2) -> 46296 | AA8: =IF(2<=Inputs!$C$11,IF(Inputs!$C$24="Serviced Monthly",F12,0)+IF(2=Inputs!$C$11,Inputs!$C$14+Inputs!$D$17,0),0) -> 25089.041 | AB8: =AA8-IF(2<=Inputs!$C$11,M12,0)-IF(2=Inputs!$C$11,Inputs!$C$37+Inputs!$D$36,0) -> 10833.904
B9: =Inputs!$C$10 -> 46235 | C9: Admin / other fee – deducted at source | E9: 0 | F9: 0 | G9: =Inputs!$C$18 -> 0 | H9: =Inputs!$C$14 -> 3700000 | I9: =Inputs!$C$18 -> 0 | L9: 0 | M9: 0 | N9: 0 | O9: =Inputs!$C$37 -> 2775000 | P9: =N9-L9 -> 0 | R9: Admin fee earned | S9: 0 | T9: 0 | U9: =Inputs!$C$18 -> 0 | V9: =Inputs!$C$38 -> 925000 | W9: =U9-S9 -> 0 | Z9: =EDATE(Inputs!$C$10,3) -> 46327 | AA9: =IF(3<=Inputs!$C$11,IF(Inputs!$C$24="Serviced Monthly",F13,0)+IF(3=Inputs!$C$11,Inputs!$C$14+Inputs!$D$17,0),0) -> 25925.342 | AB9: =AA9-IF(3<=Inputs!$C$11,M13,0)-IF(3=Inputs!$C$11,Inputs!$C$37+Inputs!$D$36,0) -> 11195.034
B10: =Inputs!$C$10 -> 46235 | C10: Interest reserve retained | E10: 0 | F10: 0 | G10: =Inputs!$C$25 -> 0 | H10: =Inputs!$C$14 -> 3700000 | I10: =Inputs!$C$25 -> 0 | L10: 0 | M10: 0 | N10: 0 | O10: =Inputs!$C$37 -> 2775000 | P10: =N10-L10 -> 0 | R10: Interest reserve retained by REL | S10: 0 | T10: 0 | U10: =Inputs!$C$25 -> 0 | V10: =Inputs!$C$38 -> 925000 | W10: =U10-S10 -> 0 | Z10: =EDATE(Inputs!$C$10,4) -> 46357 | AA10: =IF(4<=Inputs!$C$11,IF(Inputs!$C$24="Serviced Monthly",F14,0)+IF(4=Inputs!$C$11,Inputs!$C$14+Inputs!$D$17,0),0) -> 25089.041 | AB10: =AA10-IF(4<=Inputs!$C$11,M14,0)-IF(4=Inputs!$C$11,Inputs!$C$37+Inputs!$D$36,0) -> 10833.904
A11: =IF(1<=Inputs!$C$11,1,"") -> 1 | B11: =IF(1<=Inputs!$C$11,EDATE(Inputs!$C$10,1),IF(1<=Inputs!$C$11+2,EDATE(Inputs!$C$10,Inputs!$C$11),"")) -> 46266 | C11: =IF(1<=Inputs!$C$11,IF(AND(N(X11)>0,N(X11)<D11),"Interest (rate change)","Interest"),IF(1=Inputs!$C$11+1,"Exit fee ("&TEXT(Inputs!$C$17,"0.00%")&")",IF(1=Inputs!$C$11+2,"Redemption – principal repaid",""))) -> Interest | D11: =IF(1<=Inputs!$C$11,EDATE(Inputs!$C$10,1)-EDATE(Inputs!$C$10,0),"") -> 31 | E11: =IF(1<=Inputs!$C$11+2,0,"") -> 0 | F11: =IF(1<=Inputs!$C$11,Inputs!$C$14*(Inputs!$C$21*(D11-X11)+IF(Inputs!$C$22="",Inputs!$C$21,Inputs!$C$22)*X11)/365,IF(1<=Inputs!$C$11+2,0,"")) -> 25925.342 | G11: =IF(1<=Inputs!$C$11,IF(Inputs!$C$24="Serviced Monthly",F11,0),IF(1=Inputs!$C$11+1,Inputs!$D$17,IF(1=Inputs!$C$11+2,Inputs!$C$14,""))) -> 25925.342 | H11: =IF(1<=Inputs!$C$11+1,Inputs!$C$14,IF(1=Inputs!$C$11+2,0,"")) -> 3700000 | I11: =IF(1<=Inputs!$C$11+2,G11,"") -> 25925.342 | K11: =IF(Inputs!$C$37=0,"",IF(1<=Inputs!$C$11,"Senior interest",IF(1=Inputs!$C$11+1,"Senior exit fee ("&TEXT(Inputs!$C$36,"0.00%")&")",IF(1=Inputs!$C$11+2,"Senior loan repaid","")))) -> Senior interest | L11: =IF(1<=Inputs!$C$11,M11,IF(1=Inputs!$C$11+1,Inputs!$D$36,IF(1=Inputs!$C$11+2,Inputs!$C$37,""))) -> 14730.308 | M11: =IF(1<=Inputs!$C$11,Inputs!$C$37*Inputs!$C$35*D11/365,IF(1<=Inputs!$C$11+2,0,"")) -> 14730.308 | N11: =IF(1<=Inputs!$C$11+2,0,"") -> 0 | O11: =IF(1<=Inputs!$C$11+1,Inputs!$C$37,IF(1=Inputs!$C$11+2,0,"")) -> 2775000 | P11: =IF(1<=Inputs!$C$11+2,N11-L11,"") -> -14730.308 | R11: =IF(1<=Inputs!$C$11,"Net interest margin",IF(1=Inputs!$C$11+1,"Net exit fee",IF(1=Inputs!$C$11+2,"Redemption in / senior repaid",""))) -> Net interest margin | S11: =IF(1<=Inputs!$C$11+2,L11,"") -> 14730.308 | T11: =IF(1<=Inputs!$C$11,F11-M11,IF(1<=Inputs!$C$11+2,0,"")) -> 11195.034 | U11: =IF(1<=Inputs!$C$11+2,G11,"") -> 25925.342 | V11: =IF(1<=Inputs!$C$11+1,Inputs!$C$38,IF(1=Inputs!$C$11+2,0,"")) -> 925000 | W11: =IF(1<=Inputs!$C$11+2,U11-S11,"") -> 11195.034 | X11: =IF(1<=Inputs!$C$11,IF(OR(Inputs!$C$23="",Inputs!$C$22=""),0,MAX(0,EDATE(Inputs!$C$10,1)-MAX(EDATE(Inputs!$C$10,0),Inputs!$C$23))),"") -> 0 | Z11: =EDATE(Inputs!$C$10,5) -> 46388 | AA11: =IF(5<=Inputs!$C$11,IF(Inputs!$C$24="Serviced Monthly",F15,0)+IF(5=Inputs!$C$11,Inputs!$C$14+Inputs!$D$17,0),0) -> 25925.342 | AB11: =AA11-IF(5<=Inputs!$C$11,M15,0)-IF(5=Inputs!$C$11,Inputs!$C$37+Inputs!$D$36,0) -> 11195.034
A12: =IF(2<=Inputs!$C$11,2,"") -> 2 | B12: =IF(2<=Inputs!$C$11,EDATE(Inputs!$C$10,2),IF(2<=Inputs!$C$11+2,EDATE(Inputs!$C$10,Inputs!$C$11),"")) -> 46296 | C12: =IF(2<=Inputs!$C$11,IF(AND(N(X12)>0,N(X12)<D12),"Interest (rate change)","Interest"),IF(2=Inputs!$C$11+1,"Exit fee ("&TEXT(Inputs!$C$17,"0.00%")&")",IF(2=Inputs!$C$11+2,"Redemption – principal repaid",""))) -> Interest | D12: =IF(2<=Inputs!$C$11,EDATE(Inputs!$C$10,2)-EDATE(Inputs!$C$10,1),"") -> 30 | E12: =IF(2<=Inputs!$C$11+2,0,"") -> 0 | F12: =IF(2<=Inputs!$C$11,Inputs!$C$14*(Inputs!$C$21*(D12-X12)+IF(Inputs!$C$22="",Inputs!$C$21,Inputs!$C$22)*X12)/365,IF(2<=Inputs!$C$11+2,0,"")) -> 25089.041 | G12: =IF(2<=Inputs!$C$11,IF(Inputs!$C$24="Serviced Monthly",F12,0),IF(2=Inputs!$C$11+1,Inputs!$D$17,IF(2=Inputs!$C$11+2,Inputs!$C$14,""))) -> 25089.041 | H12: =IF(2<=Inputs!$C$11+1,Inputs!$C$14,IF(2=Inputs!$C$11+2,0,"")) -> 3700000 | I12: =IF(2<=Inputs!$C$11+2,G12,"") -> 25089.041 | K12: =IF(Inputs!$C$37=0,"",IF(2<=Inputs!$C$11,"Senior interest",IF(2=Inputs!$C$11+1,"Senior exit fee ("&TEXT(Inputs!$C$36,"0.00%")&")",IF(2=Inputs!$C$11+2,"Senior loan repaid","")))) -> Senior interest | L12: =IF(2<=Inputs!$C$11,M12,IF(2=Inputs!$C$11+1,Inputs!$D$36,IF(2=Inputs!$C$11+2,Inputs!$C$37,""))) -> 14255.137 | M12: =IF(2<=Inputs!$C$11,Inputs!$C$37*Inputs!$C$35*D12/365,IF(2<=Inputs!$C$11+2,0,"")) -> 14255.137 | N12: =IF(2<=Inputs!$C$11+2,0,"") -> 0 | O12: =IF(2<=Inputs!$C$11+1,Inputs!$C$37,IF(2=Inputs!$C$11+2,0,"")) -> 2775000 | P12: =IF(2<=Inputs!$C$11+2,N12-L12,"") -> -14255.137 | R12: =IF(2<=Inputs!$C$11,"Net interest margin",IF(2=Inputs!$C$11+1,"Net exit fee",IF(2=Inputs!$C$11+2,"Redemption in / senior repaid",""))) -> Net interest margin | S12: =IF(2<=Inputs!$C$11+2,L12,"") -> 14255.137 | T12: =IF(2<=Inputs!$C$11,F12-M12,IF(2<=Inputs!$C$11+2,0,"")) -> 10833.904 | U12: =IF(2<=Inputs!$C$11+2,G12,"") -> 25089.041 | V12: =IF(2<=Inputs!$C$11+1,Inputs!$C$38,IF(2=Inputs!$C$11+2,0,"")) -> 925000 | W12: =IF(2<=Inputs!$C$11+2,U12-S12,"") -> 10833.904 | X12: =IF(2<=Inputs!$C$11,IF(OR(Inputs!$C$23="",Inputs!$C$22=""),0,MAX(0,EDATE(Inputs!$C$10,2)-MAX(EDATE(Inputs!$C$10,1),Inputs!$C$23))),"") -> 0 | Z12: =EDATE(Inputs!$C$10,6) -> 46419 | AA12: =IF(6<=Inputs!$C$11,IF(Inputs!$C$24="Serviced Monthly",F16,0)+IF(6=Inputs!$C$11,Inputs!$C$14+Inputs!$D$17,0),0) -> 25925.342 | AB12: =AA12-IF(6<=Inputs!$C$11,M16,0)-IF(6=Inputs!$C$11,Inputs!$C$37+Inputs!$D$36,0) -> 11195.034
A13: =IF(3<=Inputs!$C$11,3,"") -> 3 | B13: =IF(3<=Inputs!$C$11,EDATE(Inputs!$C$10,3),IF(3<=Inputs!$C$11+2,EDATE(Inputs!$C$10,Inputs!$C$11),"")) -> 46327 | C13: =IF(3<=Inputs!$C$11,IF(AND(N(X13)>0,N(X13)<D13),"Interest (rate change)","Interest"),IF(3=Inputs!$C$11+1,"Exit fee ("&TEXT(Inputs!$C$17,"0.00%")&")",IF(3=Inputs!$C$11+2,"Redemption – principal repaid",""))) -> Interest | D13: =IF(3<=Inputs!$C$11,EDATE(Inputs!$C$10,3)-EDATE(Inputs!$C$10,2),"") -> 31 | E13: =IF(3<=Inputs!$C$11+2,0,"") -> 0 | F13: =IF(3<=Inputs!$C$11,Inputs!$C$14*(Inputs!$C$21*(D13-X13)+IF(Inputs!$C$22="",Inputs!$C$21,Inputs!$C$22)*X13)/365,IF(3<=Inputs!$C$11+2,0,"")) -> 25925.342 | G13: =IF(3<=Inputs!$C$11,IF(Inputs!$C$24="Serviced Monthly",F13,0),IF(3=Inputs!$C$11+1,Inputs!$D$17,IF(3=Inputs!$C$11+2,Inputs!$C$14,""))) -> 25925.342 | H13: =IF(3<=Inputs!$C$11+1,Inputs!$C$14,IF(3=Inputs!$C$11+2,0,"")) -> 3700000 | I13: =IF(3<=Inputs!$C$11+2,G13,"") -> 25925.342 | K13: =IF(Inputs!$C$37=0,"",IF(3<=Inputs!$C$11,"Senior interest",IF(3=Inputs!$C$11+1,"Senior exit fee ("&TEXT(Inputs!$C$36,"0.00%")&")",IF(3=Inputs!$C$11+2,"Senior loan repaid","")))) -> Senior interest | L13: =IF(3<=Inputs!$C$11,M13,IF(3=Inputs!$C$11+1,Inputs!$D$36,IF(3=Inputs!$C$11+2,Inputs!$C$37,""))) -> 14730.308 | M13: =IF(3<=Inputs!$C$11,Inputs!$C$37*Inputs!$C$35*D13/365,IF(3<=Inputs!$C$11+2,0,"")) -> 14730.308 | N13: =IF(3<=Inputs!$C$11+2,0,"") -> 0 | O13: =IF(3<=Inputs!$C$11+1,Inputs!$C$37,IF(3=Inputs!$C$11+2,0,"")) -> 2775000 | P13: =IF(3<=Inputs!$C$11+2,N13-L13,"") -> -14730.308 | R13: =IF(3<=Inputs!$C$11,"Net interest margin",IF(3=Inputs!$C$11+1,"Net exit fee",IF(3=Inputs!$C$11+2,"Redemption in / senior repaid",""))) -> Net interest margin | S13: =IF(3<=Inputs!$C$11+2,L13,"") -> 14730.308 | T13: =IF(3<=Inputs!$C$11,F13-M13,IF(3<=Inputs!$C$11+2,0,"")) -> 11195.034 | U13: =IF(3<=Inputs!$C$11+2,G13,"") -> 25925.342 | V13: =IF(3<=Inputs!$C$11+1,Inputs!$C$38,IF(3=Inputs!$C$11+2,0,"")) -> 925000 | W13: =IF(3<=Inputs!$C$11+2,U13-S13,"") -> 11195.034 | X13: =IF(3<=Inputs!$C$11,IF(OR(Inputs!$C$23="",Inputs!$C$22=""),0,MAX(0,EDATE(Inputs!$C$10,3)-MAX(EDATE(Inputs!$C$10,2),Inputs!$C$23))),"") -> 0 | Z13: =EDATE(Inputs!$C$10,7) -> 46447 | AA13: =IF(7<=Inputs!$C$11,IF(Inputs!$C$24="Serviced Monthly",F17,0)+IF(7=Inputs!$C$11,Inputs!$C$14+Inputs!$D$17,0),0) -> 23416.438 | AB13: =AA13-IF(7<=Inputs!$C$11,M17,0)-IF(7=Inputs!$C$11,Inputs!$C$37+Inputs!$D$36,0) -> 10111.644
A14: =IF(4<=Inputs!$C$11,4,"") -> 4 | B14: =IF(4<=Inputs!$C$11,EDATE(Inputs!$C$10,4),IF(4<=Inputs!$C$11+2,EDATE(Inputs!$C$10,Inputs!$C$11),"")) -> 46357 | C14: =IF(4<=Inputs!$C$11,IF(AND(N(X14)>0,N(X14)<D14),"Interest (rate change)","Interest"),IF(4=Inputs!$C$11+1,"Exit fee ("&TEXT(Inputs!$C$17,"0.00%")&")",IF(4=Inputs!$C$11+2,"Redemption – principal repaid",""))) -> Interest | D14: =IF(4<=Inputs!$C$11,EDATE(Inputs!$C$10,4)-EDATE(Inputs!$C$10,3),"") -> 30 | E14: =IF(4<=Inputs!$C$11+2,0,"") -> 0 | F14: =IF(4<=Inputs!$C$11,Inputs!$C$14*(Inputs!$C$21*(D14-X14)+IF(Inputs!$C$22="",Inputs!$C$21,Inputs!$C$22)*X14)/365,IF(4<=Inputs!$C$11+2,0,"")) -> 25089.041 | G14: =IF(4<=Inputs!$C$11,IF(Inputs!$C$24="Serviced Monthly",F14,0),IF(4=Inputs!$C$11+1,Inputs!$D$17,IF(4=Inputs!$C$11+2,Inputs!$C$14,""))) -> 25089.041 | H14: =IF(4<=Inputs!$C$11+1,Inputs!$C$14,IF(4=Inputs!$C$11+2,0,"")) -> 3700000 | I14: =IF(4<=Inputs!$C$11+2,G14,"") -> 25089.041 | K14: =IF(Inputs!$C$37=0,"",IF(4<=Inputs!$C$11,"Senior interest",IF(4=Inputs!$C$11+1,"Senior exit fee ("&TEXT(Inputs!$C$36,"0.00%")&")",IF(4=Inputs!$C$11+2,"Senior loan repaid","")))) -> Senior interest | L14: =IF(4<=Inputs!$C$11,M14,IF(4=Inputs!$C$11+1,Inputs!$D$36,IF(4=Inputs!$C$11+2,Inputs!$C$37,""))) -> 14255.137 | M14: =IF(4<=Inputs!$C$11,Inputs!$C$37*Inputs!$C$35*D14/365,IF(4<=Inputs!$C$11+2,0,"")) -> 14255.137 | N14: =IF(4<=Inputs!$C$11+2,0,"") -> 0 | O14: =IF(4<=Inputs!$C$11+1,Inputs!$C$37,IF(4=Inputs!$C$11+2,0,"")) -> 2775000 | P14: =IF(4<=Inputs!$C$11+2,N14-L14,"") -> -14255.137 | R14: =IF(4<=Inputs!$C$11,"Net interest margin",IF(4=Inputs!$C$11+1,"Net exit fee",IF(4=Inputs!$C$11+2,"Redemption in / senior repaid",""))) -> Net interest margin | S14: =IF(4<=Inputs!$C$11+2,L14,"") -> 14255.137 | T14: =IF(4<=Inputs!$C$11,F14-M14,IF(4<=Inputs!$C$11+2,0,"")) -> 10833.904 | U14: =IF(4<=Inputs!$C$11+2,G14,"") -> 25089.041 | V14: =IF(4<=Inputs!$C$11+1,Inputs!$C$38,IF(4=Inputs!$C$11+2,0,"")) -> 925000 | W14: =IF(4<=Inputs!$C$11+2,U14-S14,"") -> 10833.904 | X14: =IF(4<=Inputs!$C$11,IF(OR(Inputs!$C$23="",Inputs!$C$22=""),0,MAX(0,EDATE(Inputs!$C$10,4)-MAX(EDATE(Inputs!$C$10,3),Inputs!$C$23))),"") -> 0 | Z14: =EDATE(Inputs!$C$10,8) -> 46478 | AA14: =IF(8<=Inputs!$C$11,IF(Inputs!$C$24="Serviced Monthly",F18,0)+IF(8=Inputs!$C$11,Inputs!$C$14+Inputs!$D$17,0),0) -> 25925.342 | AB14: =AA14-IF(8<=Inputs!$C$11,M18,0)-IF(8=Inputs!$C$11,Inputs!$C$37+Inputs!$D$36,0) -> 11195.034
A15: =IF(5<=Inputs!$C$11,5,"") -> 5 | B15: =IF(5<=Inputs!$C$11,EDATE(Inputs!$C$10,5),IF(5<=Inputs!$C$11+2,EDATE(Inputs!$C$10,Inputs!$C$11),"")) -> 46388 | C15: =IF(5<=Inputs!$C$11,IF(AND(N(X15)>0,N(X15)<D15),"Interest (rate change)","Interest"),IF(5=Inputs!$C$11+1,"Exit fee ("&TEXT(Inputs!$C$17,"0.00%")&")",IF(5=Inputs!$C$11+2,"Redemption – principal repaid",""))) -> Interest | D15: =IF(5<=Inputs!$C$11,EDATE(Inputs!$C$10,5)-EDATE(Inputs!$C$10,4),"") -> 31 | E15: =IF(5<=Inputs!$C$11+2,0,"") -> 0 | F15: =IF(5<=Inputs!$C$11,Inputs!$C$14*(Inputs!$C$21*(D15-X15)+IF(Inputs!$C$22="",Inputs!$C$21,Inputs!$C$22)*X15)/365,IF(5<=Inputs!$C$11+2,0,"")) -> 25925.342 | G15: =IF(5<=Inputs!$C$11,IF(Inputs!$C$24="Serviced Monthly",F15,0),IF(5=Inputs!$C$11+1,Inputs!$D$17,IF(5=Inputs!$C$11+2,Inputs!$C$14,""))) -> 25925.342 | H15: =IF(5<=Inputs!$C$11+1,Inputs!$C$14,IF(5=Inputs!$C$11+2,0,"")) -> 3700000 | I15: =IF(5<=Inputs!$C$11+2,G15,"") -> 25925.342 | K15: =IF(Inputs!$C$37=0,"",IF(5<=Inputs!$C$11,"Senior interest",IF(5=Inputs!$C$11+1,"Senior exit fee ("&TEXT(Inputs!$C$36,"0.00%")&")",IF(5=Inputs!$C$11+2,"Senior loan repaid","")))) -> Senior interest | L15: =IF(5<=Inputs!$C$11,M15,IF(5=Inputs!$C$11+1,Inputs!$D$36,IF(5=Inputs!$C$11+2,Inputs!$C$37,""))) -> 14730.308 | M15: =IF(5<=Inputs!$C$11,Inputs!$C$37*Inputs!$C$35*D15/365,IF(5<=Inputs!$C$11+2,0,"")) -> 14730.308 | N15: =IF(5<=Inputs!$C$11+2,0,"") -> 0 | O15: =IF(5<=Inputs!$C$11+1,Inputs!$C$37,IF(5=Inputs!$C$11+2,0,"")) -> 2775000 | P15: =IF(5<=Inputs!$C$11+2,N15-L15,"") -> -14730.308 | R15: =IF(5<=Inputs!$C$11,"Net interest margin",IF(5=Inputs!$C$11+1,"Net exit fee",IF(5=Inputs!$C$11+2,"Redemption in / senior repaid",""))) -> Net interest margin | S15: =IF(5<=Inputs!$C$11+2,L15,"") -> 14730.308 | T15: =IF(5<=Inputs!$C$11,F15-M15,IF(5<=Inputs!$C$11+2,0,"")) -> 11195.034 | U15: =IF(5<=Inputs!$C$11+2,G15,"") -> 25925.342 | V15: =IF(5<=Inputs!$C$11+1,Inputs!$C$38,IF(5=Inputs!$C$11+2,0,"")) -> 925000 | W15: =IF(5<=Inputs!$C$11+2,U15-S15,"") -> 11195.034 | X15: =IF(5<=Inputs!$C$11,IF(OR(Inputs!$C$23="",Inputs!$C$22=""),0,MAX(0,EDATE(Inputs!$C$10,5)-MAX(EDATE(Inputs!$C$10,4),Inputs!$C$23))),"") -> 0 | Z15: =EDATE(Inputs!$C$10,9) -> 46508 | AA15: =IF(9<=Inputs!$C$11,IF(Inputs!$C$24="Serviced Monthly",F19,0)+IF(9=Inputs!$C$11,Inputs!$C$14+Inputs!$D$17,0),0) -> 25089.041 | AB15: =AA15-IF(9<=Inputs!$C$11,M19,0)-IF(9=Inputs!$C$11,Inputs!$C$37+Inputs!$D$36,0) -> 10833.904
A16: =IF(6<=Inputs!$C$11,6,"") -> 6 | B16: =IF(6<=Inputs!$C$11,EDATE(Inputs!$C$10,6),IF(6<=Inputs!$C$11+2,EDATE(Inputs!$C$10,Inputs!$C$11),"")) -> 46419 | C16: =IF(6<=Inputs!$C$11,IF(AND(N(X16)>0,N(X16)<D16),"Interest (rate change)","Interest"),IF(6=Inputs!$C$11+1,"Exit fee ("&TEXT(Inputs!$C$17,"0.00%")&")",IF(6=Inputs!$C$11+2,"Redemption – principal repaid",""))) -> Interest | D16: =IF(6<=Inputs!$C$11,EDATE(Inputs!$C$10,6)-EDATE(Inputs!$C$10,5),"") -> 31 | E16: =IF(6<=Inputs!$C$11+2,0,"") -> 0 | F16: =IF(6<=Inputs!$C$11,Inputs!$C$14*(Inputs!$C$21*(D16-X16)+IF(Inputs!$C$22="",Inputs!$C$21,Inputs!$C$22)*X16)/365,IF(6<=Inputs!$C$11+2,0,"")) -> 25925.342 | G16: =IF(6<=Inputs!$C$11,IF(Inputs!$C$24="Serviced Monthly",F16,0),IF(6=Inputs!$C$11+1,Inputs!$D$17,IF(6=Inputs!$C$11+2,Inputs!$C$14,""))) -> 25925.342 | H16: =IF(6<=Inputs!$C$11+1,Inputs!$C$14,IF(6=Inputs!$C$11+2,0,"")) -> 3700000 | I16: =IF(6<=Inputs!$C$11+2,G16,"") -> 25925.342 | K16: =IF(Inputs!$C$37=0,"",IF(6<=Inputs!$C$11,"Senior interest",IF(6=Inputs!$C$11+1,"Senior exit fee ("&TEXT(Inputs!$C$36,"0.00%")&")",IF(6=Inputs!$C$11+2,"Senior loan repaid","")))) -> Senior interest | L16: =IF(6<=Inputs!$C$11,M16,IF(6=Inputs!$C$11+1,Inputs!$D$36,IF(6=Inputs!$C$11+2,Inputs!$C$37,""))) -> 14730.308 | M16: =IF(6<=Inputs!$C$11,Inputs!$C$37*Inputs!$C$35*D16/365,IF(6<=Inputs!$C$11+2,0,"")) -> 14730.308 | N16: =IF(6<=Inputs!$C$11+2,0,"") -> 0 | O16: =IF(6<=Inputs!$C$11+1,Inputs!$C$37,IF(6=Inputs!$C$11+2,0,"")) -> 2775000 | P16: =IF(6<=Inputs!$C$11+2,N16-L16,"") -> -14730.308 | R16: =IF(6<=Inputs!$C$11,"Net interest margin",IF(6=Inputs!$C$11+1,"Net exit fee",IF(6=Inputs!$C$11+2,"Redemption in / senior repaid",""))) -> Net interest margin | S16: =IF(6<=Inputs!$C$11+2,L16,"") -> 14730.308 | T16: =IF(6<=Inputs!$C$11,F16-M16,IF(6<=Inputs!$C$11+2,0,"")) -> 11195.034 | U16: =IF(6<=Inputs!$C$11+2,G16,"") -> 25925.342 | V16: =IF(6<=Inputs!$C$11+1,Inputs!$C$38,IF(6=Inputs!$C$11+2,0,"")) -> 925000 | W16: =IF(6<=Inputs!$C$11+2,U16-S16,"") -> 11195.034 | X16: =IF(6<=Inputs!$C$11,IF(OR(Inputs!$C$23="",Inputs!$C$22=""),0,MAX(0,EDATE(Inputs!$C$10,6)-MAX(EDATE(Inputs!$C$10,5),Inputs!$C$23))),"") -> 0 | Z16: =EDATE(Inputs!$C$10,10) -> 46539 | AA16: =IF(10<=Inputs!$C$11,IF(Inputs!$C$24="Serviced Monthly",F20,0)+IF(10=Inputs!$C$11,Inputs!$C$14+Inputs!$D$17,0),0) -> 25925.342 | AB16: =AA16-IF(10<=Inputs!$C$11,M20,0)-IF(10=Inputs!$C$11,Inputs!$C$37+Inputs!$D$36,0) -> 11195.034
A17: =IF(7<=Inputs!$C$11,7,"") -> 7 | B17: =IF(7<=Inputs!$C$11,EDATE(Inputs!$C$10,7),IF(7<=Inputs!$C$11+2,EDATE(Inputs!$C$10,Inputs!$C$11),"")) -> 46447 | C17: =IF(7<=Inputs!$C$11,IF(AND(N(X17)>0,N(X17)<D17),"Interest (rate change)","Interest"),IF(7=Inputs!$C$11+1,"Exit fee ("&TEXT(Inputs!$C$17,"0.00%")&")",IF(7=Inputs!$C$11+2,"Redemption – principal repaid",""))) -> Interest | D17: =IF(7<=Inputs!$C$11,EDATE(Inputs!$C$10,7)-EDATE(Inputs!$C$10,6),"") -> 28 | E17: =IF(7<=Inputs!$C$11+2,0,"") -> 0 | F17: =IF(7<=Inputs!$C$11,Inputs!$C$14*(Inputs!$C$21*(D17-X17)+IF(Inputs!$C$22="",Inputs!$C$21,Inputs!$C$22)*X17)/365,IF(7<=Inputs!$C$11+2,0,"")) -> 23416.438 | G17: =IF(7<=Inputs!$C$11,IF(Inputs!$C$24="Serviced Monthly",F17,0),IF(7=Inputs!$C$11+1,Inputs!$D$17,IF(7=Inputs!$C$11+2,Inputs!$C$14,""))) -> 23416.438 | H17: =IF(7<=Inputs!$C$11+1,Inputs!$C$14,IF(7=Inputs!$C$11+2,0,"")) -> 3700000 | I17: =IF(7<=Inputs!$C$11+2,G17,"") -> 23416.438 | K17: =IF(Inputs!$C$37=0,"",IF(7<=Inputs!$C$11,"Senior interest",IF(7=Inputs!$C$11+1,"Senior exit fee ("&TEXT(Inputs!$C$36,"0.00%")&")",IF(7=Inputs!$C$11+2,"Senior loan repaid","")))) -> Senior interest | L17: =IF(7<=Inputs!$C$11,M17,IF(7=Inputs!$C$11+1,Inputs!$D$36,IF(7=Inputs!$C$11+2,Inputs!$C$37,""))) -> 13304.795 | M17: =IF(7<=Inputs!$C$11,Inputs!$C$37*Inputs!$C$35*D17/365,IF(7<=Inputs!$C$11+2,0,"")) -> 13304.795 | N17: =IF(7<=Inputs!$C$11+2,0,"") -> 0 | O17: =IF(7<=Inputs!$C$11+1,Inputs!$C$37,IF(7=Inputs!$C$11+2,0,"")) -> 2775000 | P17: =IF(7<=Inputs!$C$11+2,N17-L17,"") -> -13304.795 | R17: =IF(7<=Inputs!$C$11,"Net interest margin",IF(7=Inputs!$C$11+1,"Net exit fee",IF(7=Inputs!$C$11+2,"Redemption in / senior repaid",""))) -> Net interest margin | S17: =IF(7<=Inputs!$C$11+2,L17,"") -> 13304.795 | T17: =IF(7<=Inputs!$C$11,F17-M17,IF(7<=Inputs!$C$11+2,0,"")) -> 10111.644 | U17: =IF(7<=Inputs!$C$11+2,G17,"") -> 23416.438 | V17: =IF(7<=Inputs!$C$11+1,Inputs!$C$38,IF(7=Inputs!$C$11+2,0,"")) -> 925000 | W17: =IF(7<=Inputs!$C$11+2,U17-S17,"") -> 10111.644 | X17: =IF(7<=Inputs!$C$11,IF(OR(Inputs!$C$23="",Inputs!$C$22=""),0,MAX(0,EDATE(Inputs!$C$10,7)-MAX(EDATE(Inputs!$C$10,6),Inputs!$C$23))),"") -> 0 | Z17: =EDATE(Inputs!$C$10,11) -> 46569 | AA17: =IF(11<=Inputs!$C$11,IF(Inputs!$C$24="Serviced Monthly",F21,0)+IF(11=Inputs!$C$11,Inputs!$C$14+Inputs!$D$17,0),0) -> 25089.041 | AB17: =AA17-IF(11<=Inputs!$C$11,M21,0)-IF(11=Inputs!$C$11,Inputs!$C$37+Inputs!$D$36,0) -> 10833.904
A18: =IF(8<=Inputs!$C$11,8,"") -> 8 | B18: =IF(8<=Inputs!$C$11,EDATE(Inputs!$C$10,8),IF(8<=Inputs!$C$11+2,EDATE(Inputs!$C$10,Inputs!$C$11),"")) -> 46478 | C18: =IF(8<=Inputs!$C$11,IF(AND(N(X18)>0,N(X18)<D18),"Interest (rate change)","Interest"),IF(8=Inputs!$C$11+1,"Exit fee ("&TEXT(Inputs!$C$17,"0.00%")&")",IF(8=Inputs!$C$11+2,"Redemption – principal repaid",""))) -> Interest | D18: =IF(8<=Inputs!$C$11,EDATE(Inputs!$C$10,8)-EDATE(Inputs!$C$10,7),"") -> 31 | E18: =IF(8<=Inputs!$C$11+2,0,"") -> 0 | F18: =IF(8<=Inputs!$C$11,Inputs!$C$14*(Inputs!$C$21*(D18-X18)+IF(Inputs!$C$22="",Inputs!$C$21,Inputs!$C$22)*X18)/365,IF(8<=Inputs!$C$11+2,0,"")) -> 25925.342 | G18: =IF(8<=Inputs!$C$11,IF(Inputs!$C$24="Serviced Monthly",F18,0),IF(8=Inputs!$C$11+1,Inputs!$D$17,IF(8=Inputs!$C$11+2,Inputs!$C$14,""))) -> 25925.342 | H18: =IF(8<=Inputs!$C$11+1,Inputs!$C$14,IF(8=Inputs!$C$11+2,0,"")) -> 3700000 | I18: =IF(8<=Inputs!$C$11+2,G18,"") -> 25925.342 | K18: =IF(Inputs!$C$37=0,"",IF(8<=Inputs!$C$11,"Senior interest",IF(8=Inputs!$C$11+1,"Senior exit fee ("&TEXT(Inputs!$C$36,"0.00%")&")",IF(8=Inputs!$C$11+2,"Senior loan repaid","")))) -> Senior interest | L18: =IF(8<=Inputs!$C$11,M18,IF(8=Inputs!$C$11+1,Inputs!$D$36,IF(8=Inputs!$C$11+2,Inputs!$C$37,""))) -> 14730.308 | M18: =IF(8<=Inputs!$C$11,Inputs!$C$37*Inputs!$C$35*D18/365,IF(8<=Inputs!$C$11+2,0,"")) -> 14730.308 | N18: =IF(8<=Inputs!$C$11+2,0,"") -> 0 | O18: =IF(8<=Inputs!$C$11+1,Inputs!$C$37,IF(8=Inputs!$C$11+2,0,"")) -> 2775000 | P18: =IF(8<=Inputs!$C$11+2,N18-L18,"") -> -14730.308 | R18: =IF(8<=Inputs!$C$11,"Net interest margin",IF(8=Inputs!$C$11+1,"Net exit fee",IF(8=Inputs!$C$11+2,"Redemption in / senior repaid",""))) -> Net interest margin | S18: =IF(8<=Inputs!$C$11+2,L18,"") -> 14730.308 | T18: =IF(8<=Inputs!$C$11,F18-M18,IF(8<=Inputs!$C$11+2,0,"")) -> 11195.034 | U18: =IF(8<=Inputs!$C$11+2,G18,"") -> 25925.342 | V18: =IF(8<=Inputs!$C$11+1,Inputs!$C$38,IF(8=Inputs!$C$11+2,0,"")) -> 925000 | W18: =IF(8<=Inputs!$C$11+2,U18-S18,"") -> 11195.034 | X18: =IF(8<=Inputs!$C$11,IF(OR(Inputs!$C$23="",Inputs!$C$22=""),0,MAX(0,EDATE(Inputs!$C$10,8)-MAX(EDATE(Inputs!$C$10,7),Inputs!$C$23))),"") -> 0 | Z18: =EDATE(Inputs!$C$10,12) -> 46600 | AA18: =IF(12<=Inputs!$C$11,IF(Inputs!$C$24="Serviced Monthly",F22,0)+IF(12=Inputs!$C$11,Inputs!$C$14+Inputs!$D$17,0),0) -> 25925.342 | AB18: =AA18-IF(12<=Inputs!$C$11,M22,0)-IF(12=Inputs!$C$11,Inputs!$C$37+Inputs!$D$36,0) -> 11195.034
A19: =IF(9<=Inputs!$C$11,9,"") -> 9 | B19: =IF(9<=Inputs!$C$11,EDATE(Inputs!$C$10,9),IF(9<=Inputs!$C$11+2,EDATE(Inputs!$C$10,Inputs!$C$11),"")) -> 46508 | C19: =IF(9<=Inputs!$C$11,IF(AND(N(X19)>0,N(X19)<D19),"Interest (rate change)","Interest"),IF(9=Inputs!$C$11+1,"Exit fee ("&TEXT(Inputs!$C$17,"0.00%")&")",IF(9=Inputs!$C$11+2,"Redemption – principal repaid",""))) -> Interest | D19: =IF(9<=Inputs!$C$11,EDATE(Inputs!$C$10,9)-EDATE(Inputs!$C$10,8),"") -> 30 | E19: =IF(9<=Inputs!$C$11+2,0,"") -> 0 | F19: =IF(9<=Inputs!$C$11,Inputs!$C$14*(Inputs!$C$21*(D19-X19)+IF(Inputs!$C$22="",Inputs!$C$21,Inputs!$C$22)*X19)/365,IF(9<=Inputs!$C$11+2,0,"")) -> 25089.041 | G19: =IF(9<=Inputs!$C$11,IF(Inputs!$C$24="Serviced Monthly",F19,0),IF(9=Inputs!$C$11+1,Inputs!$D$17,IF(9=Inputs!$C$11+2,Inputs!$C$14,""))) -> 25089.041 | H19: =IF(9<=Inputs!$C$11+1,Inputs!$C$14,IF(9=Inputs!$C$11+2,0,"")) -> 3700000 | I19: =IF(9<=Inputs!$C$11+2,G19,"") -> 25089.041 | K19: =IF(Inputs!$C$37=0,"",IF(9<=Inputs!$C$11,"Senior interest",IF(9=Inputs!$C$11+1,"Senior exit fee ("&TEXT(Inputs!$C$36,"0.00%")&")",IF(9=Inputs!$C$11+2,"Senior loan repaid","")))) -> Senior interest | L19: =IF(9<=Inputs!$C$11,M19,IF(9=Inputs!$C$11+1,Inputs!$D$36,IF(9=Inputs!$C$11+2,Inputs!$C$37,""))) -> 14255.137 | M19: =IF(9<=Inputs!$C$11,Inputs!$C$37*Inputs!$C$35*D19/365,IF(9<=Inputs!$C$11+2,0,"")) -> 14255.137 | N19: =IF(9<=Inputs!$C$11+2,0,"") -> 0 | O19: =IF(9<=Inputs!$C$11+1,Inputs!$C$37,IF(9=Inputs!$C$11+2,0,"")) -> 2775000 | P19: =IF(9<=Inputs!$C$11+2,N19-L19,"") -> -14255.137 | R19: =IF(9<=Inputs!$C$11,"Net interest margin",IF(9=Inputs!$C$11+1,"Net exit fee",IF(9=Inputs!$C$11+2,"Redemption in / senior repaid",""))) -> Net interest margin | S19: =IF(9<=Inputs!$C$11+2,L19,"") -> 14255.137 | T19: =IF(9<=Inputs!$C$11,F19-M19,IF(9<=Inputs!$C$11+2,0,"")) -> 10833.904 | U19: =IF(9<=Inputs!$C$11+2,G19,"") -> 25089.041 | V19: =IF(9<=Inputs!$C$11+1,Inputs!$C$38,IF(9=Inputs!$C$11+2,0,"")) -> 925000 | W19: =IF(9<=Inputs!$C$11+2,U19-S19,"") -> 10833.904 | X19: =IF(9<=Inputs!$C$11,IF(OR(Inputs!$C$23="",Inputs!$C$22=""),0,MAX(0,EDATE(Inputs!$C$10,9)-MAX(EDATE(Inputs!$C$10,8),Inputs!$C$23))),"") -> 0 | Z19: =EDATE(Inputs!$C$10,13) -> 46631 | AA19: =IF(13<=Inputs!$C$11,IF(Inputs!$C$24="Serviced Monthly",F23,0)+IF(13=Inputs!$C$11,Inputs!$C$14+Inputs!$D$17,0),0) -> 25925.342 | AB19: =AA19-IF(13<=Inputs!$C$11,M23,0)-IF(13=Inputs!$C$11,Inputs!$C$37+Inputs!$D$36,0) -> 11195.034
A20: =IF(10<=Inputs!$C$11,10,"") -> 10 | B20: =IF(10<=Inputs!$C$11,EDATE(Inputs!$C$10,10),IF(10<=Inputs!$C$11+2,EDATE(Inputs!$C$10,Inputs!$C$11),"")) -> 46539 | C20: =IF(10<=Inputs!$C$11,IF(AND(N(X20)>0,N(X20)<D20),"Interest (rate change)","Interest"),IF(10=Inputs!$C$11+1,"Exit fee ("&TEXT(Inputs!$C$17,"0.00%")&")",IF(10=Inputs!$C$11+2,"Redemption – principal repaid",""))) -> Interest | D20: =IF(10<=Inputs!$C$11,EDATE(Inputs!$C$10,10)-EDATE(Inputs!$C$10,9),"") -> 31 | E20: =IF(10<=Inputs!$C$11+2,0,"") -> 0 | F20: =IF(10<=Inputs!$C$11,Inputs!$C$14*(Inputs!$C$21*(D20-X20)+IF(Inputs!$C$22="",Inputs!$C$21,Inputs!$C$22)*X20)/365,IF(10<=Inputs!$C$11+2,0,"")) -> 25925.342 | G20: =IF(10<=Inputs!$C$11,IF(Inputs!$C$24="Serviced Monthly",F20,0),IF(10=Inputs!$C$11+1,Inputs!$D$17,IF(10=Inputs!$C$11+2,Inputs!$C$14,""))) -> 25925.342 | H20: =IF(10<=Inputs!$C$11+1,Inputs!$C$14,IF(10=Inputs!$C$11+2,0,"")) -> 3700000 | I20: =IF(10<=Inputs!$C$11+2,G20,"") -> 25925.342 | K20: =IF(Inputs!$C$37=0,"",IF(10<=Inputs!$C$11,"Senior interest",IF(10=Inputs!$C$11+1,"Senior exit fee ("&TEXT(Inputs!$C$36,"0.00%")&")",IF(10=Inputs!$C$11+2,"Senior loan repaid","")))) -> Senior interest | L20: =IF(10<=Inputs!$C$11,M20,IF(10=Inputs!$C$11+1,Inputs!$D$36,IF(10=Inputs!$C$11+2,Inputs!$C$37,""))) -> 14730.308 | M20: =IF(10<=Inputs!$C$11,Inputs!$C$37*Inputs!$C$35*D20/365,IF(10<=Inputs!$C$11+2,0,"")) -> 14730.308 | N20: =IF(10<=Inputs!$C$11+2,0,"") -> 0 | O20: =IF(10<=Inputs!$C$11+1,Inputs!$C$37,IF(10=Inputs!$C$11+2,0,"")) -> 2775000 | P20: =IF(10<=Inputs!$C$11+2,N20-L20,"") -> -14730.308 | R20: =IF(10<=Inputs!$C$11,"Net interest margin",IF(10=Inputs!$C$11+1,"Net exit fee",IF(10=Inputs!$C$11+2,"Redemption in / senior repaid",""))) -> Net interest margin | S20: =IF(10<=Inputs!$C$11+2,L20,"") -> 14730.308 | T20: =IF(10<=Inputs!$C$11,F20-M20,IF(10<=Inputs!$C$11+2,0,"")) -> 11195.034 | U20: =IF(10<=Inputs!$C$11+2,G20,"") -> 25925.342 | V20: =IF(10<=Inputs!$C$11+1,Inputs!$C$38,IF(10=Inputs!$C$11+2,0,"")) -> 925000 | W20: =IF(10<=Inputs!$C$11+2,U20-S20,"") -> 11195.034 | X20: =IF(10<=Inputs!$C$11,IF(OR(Inputs!$C$23="",Inputs!$C$22=""),0,MAX(0,EDATE(Inputs!$C$10,10)-MAX(EDATE(Inputs!$C$10,9),Inputs!$C$23))),"") -> 0 | Z20: =EDATE(Inputs!$C$10,14) -> 46661 | AA20: =IF(14<=Inputs!$C$11,IF(Inputs!$C$24="Serviced Monthly",F24,0)+IF(14=Inputs!$C$11,Inputs!$C$14+Inputs!$D$17,0),0) -> 25089.041 | AB20: =AA20-IF(14<=Inputs!$C$11,M24,0)-IF(14=Inputs!$C$11,Inputs!$C$37+Inputs!$D$36,0) -> 10833.904
A21: =IF(11<=Inputs!$C$11,11,"") -> 11 | B21: =IF(11<=Inputs!$C$11,EDATE(Inputs!$C$10,11),IF(11<=Inputs!$C$11+2,EDATE(Inputs!$C$10,Inputs!$C$11),"")) -> 46569 | C21: =IF(11<=Inputs!$C$11,IF(AND(N(X21)>0,N(X21)<D21),"Interest (rate change)","Interest"),IF(11=Inputs!$C$11+1,"Exit fee ("&TEXT(Inputs!$C$17,"0.00%")&")",IF(11=Inputs!$C$11+2,"Redemption – principal repaid",""))) -> Interest | D21: =IF(11<=Inputs!$C$11,EDATE(Inputs!$C$10,11)-EDATE(Inputs!$C$10,10),"") -> 30 | E21: =IF(11<=Inputs!$C$11+2,0,"") -> 0 | F21: =IF(11<=Inputs!$C$11,Inputs!$C$14*(Inputs!$C$21*(D21-X21)+IF(Inputs!$C$22="",Inputs!$C$21,Inputs!$C$22)*X21)/365,IF(11<=Inputs!$C$11+2,0,"")) -> 25089.041 | G21: =IF(11<=Inputs!$C$11,IF(Inputs!$C$24="Serviced Monthly",F21,0),IF(11=Inputs!$C$11+1,Inputs!$D$17,IF(11=Inputs!$C$11+2,Inputs!$C$14,""))) -> 25089.041 | H21: =IF(11<=Inputs!$C$11+1,Inputs!$C$14,IF(11=Inputs!$C$11+2,0,"")) -> 3700000 | I21: =IF(11<=Inputs!$C$11+2,G21,"") -> 25089.041 | K21: =IF(Inputs!$C$37=0,"",IF(11<=Inputs!$C$11,"Senior interest",IF(11=Inputs!$C$11+1,"Senior exit fee ("&TEXT(Inputs!$C$36,"0.00%")&")",IF(11=Inputs!$C$11+2,"Senior loan repaid","")))) -> Senior interest | L21: =IF(11<=Inputs!$C$11,M21,IF(11=Inputs!$C$11+1,Inputs!$D$36,IF(11=Inputs!$C$11+2,Inputs!$C$37,""))) -> 14255.137 | M21: =IF(11<=Inputs!$C$11,Inputs!$C$37*Inputs!$C$35*D21/365,IF(11<=Inputs!$C$11+2,0,"")) -> 14255.137 | N21: =IF(11<=Inputs!$C$11+2,0,"") -> 0 | O21: =IF(11<=Inputs!$C$11+1,Inputs!$C$37,IF(11=Inputs!$C$11+2,0,"")) -> 2775000 | P21: =IF(11<=Inputs!$C$11+2,N21-L21,"") -> -14255.137 | R21: =IF(11<=Inputs!$C$11,"Net interest margin",IF(11=Inputs!$C$11+1,"Net exit fee",IF(11=Inputs!$C$11+2,"Redemption in / senior repaid",""))) -> Net interest margin | S21: =IF(11<=Inputs!$C$11+2,L21,"") -> 14255.137 | T21: =IF(11<=Inputs!$C$11,F21-M21,IF(11<=Inputs!$C$11+2,0,"")) -> 10833.904 | U21: =IF(11<=Inputs!$C$11+2,G21,"") -> 25089.041 | V21: =IF(11<=Inputs!$C$11+1,Inputs!$C$38,IF(11=Inputs!$C$11+2,0,"")) -> 925000 | W21: =IF(11<=Inputs!$C$11+2,U21-S21,"") -> 10833.904 | X21: =IF(11<=Inputs!$C$11,IF(OR(Inputs!$C$23="",Inputs!$C$22=""),0,MAX(0,EDATE(Inputs!$C$10,11)-MAX(EDATE(Inputs!$C$10,10),Inputs!$C$23))),"") -> 0 | Z21: =EDATE(Inputs!$C$10,15) -> 46692 | AA21: =IF(15<=Inputs!$C$11,IF(Inputs!$C$24="Serviced Monthly",F25,0)+IF(15=Inputs!$C$11,Inputs!$C$14+Inputs!$D$17,0),0) -> 25925.342 | AB21: =AA21-IF(15<=Inputs!$C$11,M25,0)-IF(15=Inputs!$C$11,Inputs!$C$37+Inputs!$D$36,0) -> 11195.034
A22: =IF(12<=Inputs!$C$11,12,"") -> 12 | B22: =IF(12<=Inputs!$C$11,EDATE(Inputs!$C$10,12),IF(12<=Inputs!$C$11+2,EDATE(Inputs!$C$10,Inputs!$C$11),"")) -> 46600 | C22: =IF(12<=Inputs!$C$11,IF(AND(N(X22)>0,N(X22)<D22),"Interest (rate change)","Interest"),IF(12=Inputs!$C$11+1,"Exit fee ("&TEXT(Inputs!$C$17,"0.00%")&")",IF(12=Inputs!$C$11+2,"Redemption – principal repaid",""))) -> Interest | D22: =IF(12<=Inputs!$C$11,EDATE(Inputs!$C$10,12)-EDATE(Inputs!$C$10,11),"") -> 31 | E22: =IF(12<=Inputs!$C$11+2,0,"") -> 0 | F22: =IF(12<=Inputs!$C$11,Inputs!$C$14*(Inputs!$C$21*(D22-X22)+IF(Inputs!$C$22="",Inputs!$C$21,Inputs!$C$22)*X22)/365,IF(12<=Inputs!$C$11+2,0,"")) -> 25925.342 | G22: =IF(12<=Inputs!$C$11,IF(Inputs!$C$24="Serviced Monthly",F22,0),IF(12=Inputs!$C$11+1,Inputs!$D$17,IF(12=Inputs!$C$11+2,Inputs!$C$14,""))) -> 25925.342 | H22: =IF(12<=Inputs!$C$11+1,Inputs!$C$14,IF(12=Inputs!$C$11+2,0,"")) -> 3700000 | I22: =IF(12<=Inputs!$C$11+2,G22,"") -> 25925.342 | K22: =IF(Inputs!$C$37=0,"",IF(12<=Inputs!$C$11,"Senior interest",IF(12=Inputs!$C$11+1,"Senior exit fee ("&TEXT(Inputs!$C$36,"0.00%")&")",IF(12=Inputs!$C$11+2,"Senior loan repaid","")))) -> Senior interest | L22: =IF(12<=Inputs!$C$11,M22,IF(12=Inputs!$C$11+1,Inputs!$D$36,IF(12=Inputs!$C$11+2,Inputs!$C$37,""))) -> 14730.308 | M22: =IF(12<=Inputs!$C$11,Inputs!$C$37*Inputs!$C$35*D22/365,IF(12<=Inputs!$C$11+2,0,"")) -> 14730.308 | N22: =IF(12<=Inputs!$C$11+2,0,"") -> 0 | O22: =IF(12<=Inputs!$C$11+1,Inputs!$C$37,IF(12=Inputs!$C$11+2,0,"")) -> 2775000 | P22: =IF(12<=Inputs!$C$11+2,N22-L22,"") -> -14730.308 | R22: =IF(12<=Inputs!$C$11,"Net interest margin",IF(12=Inputs!$C$11+1,"Net exit fee",IF(12=Inputs!$C$11+2,"Redemption in / senior repaid",""))) -> Net interest margin | S22: =IF(12<=Inputs!$C$11+2,L22,"") -> 14730.308 | T22: =IF(12<=Inputs!$C$11,F22-M22,IF(12<=Inputs!$C$11+2,0,"")) -> 11195.034 | U22: =IF(12<=Inputs!$C$11+2,G22,"") -> 25925.342 | V22: =IF(12<=Inputs!$C$11+1,Inputs!$C$38,IF(12=Inputs!$C$11+2,0,"")) -> 925000 | W22: =IF(12<=Inputs!$C$11+2,U22-S22,"") -> 11195.034 | X22: =IF(12<=Inputs!$C$11,IF(OR(Inputs!$C$23="",Inputs!$C$22=""),0,MAX(0,EDATE(Inputs!$C$10,12)-MAX(EDATE(Inputs!$C$10,11),Inputs!$C$23))),"") -> 0 | Z22: =EDATE(Inputs!$C$10,16) -> 46722 | AA22: =IF(16<=Inputs!$C$11,IF(Inputs!$C$24="Serviced Monthly",F26,0)+IF(16=Inputs!$C$11,Inputs!$C$14+Inputs!$D$17,0),0) -> 25089.041 | AB22: =AA22-IF(16<=Inputs!$C$11,M26,0)-IF(16=Inputs!$C$11,Inputs!$C$37+Inputs!$D$36,0) -> 10833.904
A23: =IF(13<=Inputs!$C$11,13,"") -> 13 | B23: =IF(13<=Inputs!$C$11,EDATE(Inputs!$C$10,13),IF(13<=Inputs!$C$11+2,EDATE(Inputs!$C$10,Inputs!$C$11),"")) -> 46631 | C23: =IF(13<=Inputs!$C$11,IF(AND(N(X23)>0,N(X23)<D23),"Interest (rate change)","Interest"),IF(13=Inputs!$C$11+1,"Exit fee ("&TEXT(Inputs!$C$17,"0.00%")&")",IF(13=Inputs!$C$11+2,"Redemption – principal repaid",""))) -> Interest | D23: =IF(13<=Inputs!$C$11,EDATE(Inputs!$C$10,13)-EDATE(Inputs!$C$10,12),"") -> 31 | E23: =IF(13<=Inputs!$C$11+2,0,"") -> 0 | F23: =IF(13<=Inputs!$C$11,Inputs!$C$14*(Inputs!$C$21*(D23-X23)+IF(Inputs!$C$22="",Inputs!$C$21,Inputs!$C$22)*X23)/365,IF(13<=Inputs!$C$11+2,0,"")) -> 25925.342 | G23: =IF(13<=Inputs!$C$11,IF(Inputs!$C$24="Serviced Monthly",F23,0),IF(13=Inputs!$C$11+1,Inputs!$D$17,IF(13=Inputs!$C$11+2,Inputs!$C$14,""))) -> 25925.342 | H23: =IF(13<=Inputs!$C$11+1,Inputs!$C$14,IF(13=Inputs!$C$11+2,0,"")) -> 3700000 | I23: =IF(13<=Inputs!$C$11+2,G23,"") -> 25925.342 | K23: =IF(Inputs!$C$37=0,"",IF(13<=Inputs!$C$11,"Senior interest",IF(13=Inputs!$C$11+1,"Senior exit fee ("&TEXT(Inputs!$C$36,"0.00%")&")",IF(13=Inputs!$C$11+2,"Senior loan repaid","")))) -> Senior interest | L23: =IF(13<=Inputs!$C$11,M23,IF(13=Inputs!$C$11+1,Inputs!$D$36,IF(13=Inputs!$C$11+2,Inputs!$C$37,""))) -> 14730.308 | M23: =IF(13<=Inputs!$C$11,Inputs!$C$37*Inputs!$C$35*D23/365,IF(13<=Inputs!$C$11+2,0,"")) -> 14730.308 | N23: =IF(13<=Inputs!$C$11+2,0,"") -> 0 | O23: =IF(13<=Inputs!$C$11+1,Inputs!$C$37,IF(13=Inputs!$C$11+2,0,"")) -> 2775000 | P23: =IF(13<=Inputs!$C$11+2,N23-L23,"") -> -14730.308 | R23: =IF(13<=Inputs!$C$11,"Net interest margin",IF(13=Inputs!$C$11+1,"Net exit fee",IF(13=Inputs!$C$11+2,"Redemption in / senior repaid",""))) -> Net interest margin | S23: =IF(13<=Inputs!$C$11+2,L23,"") -> 14730.308 | T23: =IF(13<=Inputs!$C$11,F23-M23,IF(13<=Inputs!$C$11+2,0,"")) -> 11195.034 | U23: =IF(13<=Inputs!$C$11+2,G23,"") -> 25925.342 | V23: =IF(13<=Inputs!$C$11+1,Inputs!$C$38,IF(13=Inputs!$C$11+2,0,"")) -> 925000 | W23: =IF(13<=Inputs!$C$11+2,U23-S23,"") -> 11195.034 | X23: =IF(13<=Inputs!$C$11,IF(OR(Inputs!$C$23="",Inputs!$C$22=""),0,MAX(0,EDATE(Inputs!$C$10,13)-MAX(EDATE(Inputs!$C$10,12),Inputs!$C$23))),"") -> 0 | Z23: =EDATE(Inputs!$C$10,17) -> 46753 | AA23: =IF(17<=Inputs!$C$11,IF(Inputs!$C$24="Serviced Monthly",F27,0)+IF(17=Inputs!$C$11,Inputs!$C$14+Inputs!$D$17,0),0) -> 25925.342 | AB23: =AA23-IF(17<=Inputs!$C$11,M27,0)-IF(17=Inputs!$C$11,Inputs!$C$37+Inputs!$D$36,0) -> 11195.034
A24: =IF(14<=Inputs!$C$11,14,"") -> 14 | B24: =IF(14<=Inputs!$C$11,EDATE(Inputs!$C$10,14),IF(14<=Inputs!$C$11+2,EDATE(Inputs!$C$10,Inputs!$C$11),"")) -> 46661 | C24: =IF(14<=Inputs!$C$11,IF(AND(N(X24)>0,N(X24)<D24),"Interest (rate change)","Interest"),IF(14=Inputs!$C$11+1,"Exit fee ("&TEXT(Inputs!$C$17,"0.00%")&")",IF(14=Inputs!$C$11+2,"Redemption – principal repaid",""))) -> Interest | D24: =IF(14<=Inputs!$C$11,EDATE(Inputs!$C$10,14)-EDATE(Inputs!$C$10,13),"") -> 30 | E24: =IF(14<=Inputs!$C$11+2,0,"") -> 0 | F24: =IF(14<=Inputs!$C$11,Inputs!$C$14*(Inputs!$C$21*(D24-X24)+IF(Inputs!$C$22="",Inputs!$C$21,Inputs!$C$22)*X24)/365,IF(14<=Inputs!$C$11+2,0,"")) -> 25089.041 | G24: =IF(14<=Inputs!$C$11,IF(Inputs!$C$24="Serviced Monthly",F24,0),IF(14=Inputs!$C$11+1,Inputs!$D$17,IF(14=Inputs!$C$11+2,Inputs!$C$14,""))) -> 25089.041 | H24: =IF(14<=Inputs!$C$11+1,Inputs!$C$14,IF(14=Inputs!$C$11+2,0,"")) -> 3700000 | I24: =IF(14<=Inputs!$C$11+2,G24,"") -> 25089.041 | K24: =IF(Inputs!$C$37=0,"",IF(14<=Inputs!$C$11,"Senior interest",IF(14=Inputs!$C$11+1,"Senior exit fee ("&TEXT(Inputs!$C$36,"0.00%")&")",IF(14=Inputs!$C$11+2,"Senior loan repaid","")))) -> Senior interest | L24: =IF(14<=Inputs!$C$11,M24,IF(14=Inputs!$C$11+1,Inputs!$D$36,IF(14=Inputs!$C$11+2,Inputs!$C$37,""))) -> 14255.137 | M24: =IF(14<=Inputs!$C$11,Inputs!$C$37*Inputs!$C$35*D24/365,IF(14<=Inputs!$C$11+2,0,"")) -> 14255.137 | N24: =IF(14<=Inputs!$C$11+2,0,"") -> 0 | O24: =IF(14<=Inputs!$C$11+1,Inputs!$C$37,IF(14=Inputs!$C$11+2,0,"")) -> 2775000 | P24: =IF(14<=Inputs!$C$11+2,N24-L24,"") -> -14255.137 | R24: =IF(14<=Inputs!$C$11,"Net interest margin",IF(14=Inputs!$C$11+1,"Net exit fee",IF(14=Inputs!$C$11+2,"Redemption in / senior repaid",""))) -> Net interest margin | S24: =IF(14<=Inputs!$C$11+2,L24,"") -> 14255.137 | T24: =IF(14<=Inputs!$C$11,F24-M24,IF(14<=Inputs!$C$11+2,0,"")) -> 10833.904 | U24: =IF(14<=Inputs!$C$11+2,G24,"") -> 25089.041 | V24: =IF(14<=Inputs!$C$11+1,Inputs!$C$38,IF(14=Inputs!$C$11+2,0,"")) -> 925000 | W24: =IF(14<=Inputs!$C$11+2,U24-S24,"") -> 10833.904 | X24: =IF(14<=Inputs!$C$11,IF(OR(Inputs!$C$23="",Inputs!$C$22=""),0,MAX(0,EDATE(Inputs!$C$10,14)-MAX(EDATE(Inputs!$C$10,13),Inputs!$C$23))),"") -> 0 | Z24: =EDATE(Inputs!$C$10,18) -> 46784 | AA24: =IF(18<=Inputs!$C$11,IF(Inputs!$C$24="Serviced Monthly",F28,0)+IF(18=Inputs!$C$11,Inputs!$C$14+Inputs!$D$17,0),0) -> 25925.342 | AB24: =AA24-IF(18<=Inputs!$C$11,M28,0)-IF(18=Inputs!$C$11,Inputs!$C$37+Inputs!$D$36,0) -> 11195.034
A25: =IF(15<=Inputs!$C$11,15,"") -> 15 | B25: =IF(15<=Inputs!$C$11,EDATE(Inputs!$C$10,15),IF(15<=Inputs!$C$11+2,EDATE(Inputs!$C$10,Inputs!$C$11),"")) -> 46692 | C25: =IF(15<=Inputs!$C$11,IF(AND(N(X25)>0,N(X25)<D25),"Interest (rate change)","Interest"),IF(15=Inputs!$C$11+1,"Exit fee ("&TEXT(Inputs!$C$17,"0.00%")&")",IF(15=Inputs!$C$11+2,"Redemption – principal repaid",""))) -> Interest | D25: =IF(15<=Inputs!$C$11,EDATE(Inputs!$C$10,15)-EDATE(Inputs!$C$10,14),"") -> 31 | E25: =IF(15<=Inputs!$C$11+2,0,"") -> 0 | F25: =IF(15<=Inputs!$C$11,Inputs!$C$14*(Inputs!$C$21*(D25-X25)+IF(Inputs!$C$22="",Inputs!$C$21,Inputs!$C$22)*X25)/365,IF(15<=Inputs!$C$11+2,0,"")) -> 25925.342 | G25: =IF(15<=Inputs!$C$11,IF(Inputs!$C$24="Serviced Monthly",F25,0),IF(15=Inputs!$C$11+1,Inputs!$D$17,IF(15=Inputs!$C$11+2,Inputs!$C$14,""))) -> 25925.342 | H25: =IF(15<=Inputs!$C$11+1,Inputs!$C$14,IF(15=Inputs!$C$11+2,0,"")) -> 3700000 | I25: =IF(15<=Inputs!$C$11+2,G25,"") -> 25925.342 | K25: =IF(Inputs!$C$37=0,"",IF(15<=Inputs!$C$11,"Senior interest",IF(15=Inputs!$C$11+1,"Senior exit fee ("&TEXT(Inputs!$C$36,"0.00%")&")",IF(15=Inputs!$C$11+2,"Senior loan repaid","")))) -> Senior interest | L25: =IF(15<=Inputs!$C$11,M25,IF(15=Inputs!$C$11+1,Inputs!$D$36,IF(15=Inputs!$C$11+2,Inputs!$C$37,""))) -> 14730.308 | M25: =IF(15<=Inputs!$C$11,Inputs!$C$37*Inputs!$C$35*D25/365,IF(15<=Inputs!$C$11+2,0,"")) -> 14730.308 | N25: =IF(15<=Inputs!$C$11+2,0,"") -> 0 | O25: =IF(15<=Inputs!$C$11+1,Inputs!$C$37,IF(15=Inputs!$C$11+2,0,"")) -> 2775000 | P25: =IF(15<=Inputs!$C$11+2,N25-L25,"") -> -14730.308 | R25: =IF(15<=Inputs!$C$11,"Net interest margin",IF(15=Inputs!$C$11+1,"Net exit fee",IF(15=Inputs!$C$11+2,"Redemption in / senior repaid",""))) -> Net interest margin | S25: =IF(15<=Inputs!$C$11+2,L25,"") -> 14730.308 | T25: =IF(15<=Inputs!$C$11,F25-M25,IF(15<=Inputs!$C$11+2,0,"")) -> 11195.034 | U25: =IF(15<=Inputs!$C$11+2,G25,"") -> 25925.342 | V25: =IF(15<=Inputs!$C$11+1,Inputs!$C$38,IF(15=Inputs!$C$11+2,0,"")) -> 925000 | W25: =IF(15<=Inputs!$C$11+2,U25-S25,"") -> 11195.034 | X25: =IF(15<=Inputs!$C$11,IF(OR(Inputs!$C$23="",Inputs!$C$22=""),0,MAX(0,EDATE(Inputs!$C$10,15)-MAX(EDATE(Inputs!$C$10,14),Inputs!$C$23))),"") -> 0 | Z25: =EDATE(Inputs!$C$10,19) -> 46813 | AA25: =IF(19<=Inputs!$C$11,IF(Inputs!$C$24="Serviced Monthly",F29,0)+IF(19=Inputs!$C$11,Inputs!$C$14+Inputs!$D$17,0),0) -> 24252.74 | AB25: =AA25-IF(19<=Inputs!$C$11,M29,0)-IF(19=Inputs!$C$11,Inputs!$C$37+Inputs!$D$36,0) -> 10472.774
A26: =IF(16<=Inputs!$C$11,16,"") -> 16 | B26: =IF(16<=Inputs!$C$11,EDATE(Inputs!$C$10,16),IF(16<=Inputs!$C$11+2,EDATE(Inputs!$C$10,Inputs!$C$11),"")) -> 46722 | C26: =IF(16<=Inputs!$C$11,IF(AND(N(X26)>0,N(X26)<D26),"Interest (rate change)","Interest"),IF(16=Inputs!$C$11+1,"Exit fee ("&TEXT(Inputs!$C$17,"0.00%")&")",IF(16=Inputs!$C$11+2,"Redemption – principal repaid",""))) -> Interest | D26: =IF(16<=Inputs!$C$11,EDATE(Inputs!$C$10,16)-EDATE(Inputs!$C$10,15),"") -> 30 | E26: =IF(16<=Inputs!$C$11+2,0,"") -> 0 | F26: =IF(16<=Inputs!$C$11,Inputs!$C$14*(Inputs!$C$21*(D26-X26)+IF(Inputs!$C$22="",Inputs!$C$21,Inputs!$C$22)*X26)/365,IF(16<=Inputs!$C$11+2,0,"")) -> 25089.041 | G26: =IF(16<=Inputs!$C$11,IF(Inputs!$C$24="Serviced Monthly",F26,0),IF(16=Inputs!$C$11+1,Inputs!$D$17,IF(16=Inputs!$C$11+2,Inputs!$C$14,""))) -> 25089.041 | H26: =IF(16<=Inputs!$C$11+1,Inputs!$C$14,IF(16=Inputs!$C$11+2,0,"")) -> 3700000 | I26: =IF(16<=Inputs!$C$11+2,G26,"") -> 25089.041 | K26: =IF(Inputs!$C$37=0,"",IF(16<=Inputs!$C$11,"Senior interest",IF(16=Inputs!$C$11+1,"Senior exit fee ("&TEXT(Inputs!$C$36,"0.00%")&")",IF(16=Inputs!$C$11+2,"Senior loan repaid","")))) -> Senior interest | L26: =IF(16<=Inputs!$C$11,M26,IF(16=Inputs!$C$11+1,Inputs!$D$36,IF(16=Inputs!$C$11+2,Inputs!$C$37,""))) -> 14255.137 | M26: =IF(16<=Inputs!$C$11,Inputs!$C$37*Inputs!$C$35*D26/365,IF(16<=Inputs!$C$11+2,0,"")) -> 14255.137 | N26: =IF(16<=Inputs!$C$11+2,0,"") -> 0 | O26: =IF(16<=Inputs!$C$11+1,Inputs!$C$37,IF(16=Inputs!$C$11+2,0,"")) -> 2775000 | P26: =IF(16<=Inputs!$C$11+2,N26-L26,"") -> -14255.137 | R26: =IF(16<=Inputs!$C$11,"Net interest margin",IF(16=Inputs!$C$11+1,"Net exit fee",IF(16=Inputs!$C$11+2,"Redemption in / senior repaid",""))) -> Net interest margin | S26: =IF(16<=Inputs!$C$11+2,L26,"") -> 14255.137 | T26: =IF(16<=Inputs!$C$11,F26-M26,IF(16<=Inputs!$C$11+2,0,"")) -> 10833.904 | U26: =IF(16<=Inputs!$C$11+2,G26,"") -> 25089.041 | V26: =IF(16<=Inputs!$C$11+1,Inputs!$C$38,IF(16=Inputs!$C$11+2,0,"")) -> 925000 | W26: =IF(16<=Inputs!$C$11+2,U26-S26,"") -> 10833.904 | X26: =IF(16<=Inputs!$C$11,IF(OR(Inputs!$C$23="",Inputs!$C$22=""),0,MAX(0,EDATE(Inputs!$C$10,16)-MAX(EDATE(Inputs!$C$10,15),Inputs!$C$23))),"") -> 0 | Z26: =EDATE(Inputs!$C$10,20) -> 46844 | AA26: =IF(20<=Inputs!$C$11,IF(Inputs!$C$24="Serviced Monthly",F30,0)+IF(20=Inputs!$C$11,Inputs!$C$14+Inputs!$D$17,0),0) -> 25925.342 | AB26: =AA26-IF(20<=Inputs!$C$11,M30,0)-IF(20=Inputs!$C$11,Inputs!$C$37+Inputs!$D$36,0) -> 11195.034
A27: =IF(17<=Inputs!$C$11,17,"") -> 17 | B27: =IF(17<=Inputs!$C$11,EDATE(Inputs!$C$10,17),IF(17<=Inputs!$C$11+2,EDATE(Inputs!$C$10,Inputs!$C$11),"")) -> 46753 | C27: =IF(17<=Inputs!$C$11,IF(AND(N(X27)>0,N(X27)<D27),"Interest (rate change)","Interest"),IF(17=Inputs!$C$11+1,"Exit fee ("&TEXT(Inputs!$C$17,"0.00%")&")",IF(17=Inputs!$C$11+2,"Redemption – principal repaid",""))) -> Interest | D27: =IF(17<=Inputs!$C$11,EDATE(Inputs!$C$10,17)-EDATE(Inputs!$C$10,16),"") -> 31 | E27: =IF(17<=Inputs!$C$11+2,0,"") -> 0 | F27: =IF(17<=Inputs!$C$11,Inputs!$C$14*(Inputs!$C$21*(D27-X27)+IF(Inputs!$C$22="",Inputs!$C$21,Inputs!$C$22)*X27)/365,IF(17<=Inputs!$C$11+2,0,"")) -> 25925.342 | G27: =IF(17<=Inputs!$C$11,IF(Inputs!$C$24="Serviced Monthly",F27,0),IF(17=Inputs!$C$11+1,Inputs!$D$17,IF(17=Inputs!$C$11+2,Inputs!$C$14,""))) -> 25925.342 | H27: =IF(17<=Inputs!$C$11+1,Inputs!$C$14,IF(17=Inputs!$C$11+2,0,"")) -> 3700000 | I27: =IF(17<=Inputs!$C$11+2,G27,"") -> 25925.342 | K27: =IF(Inputs!$C$37=0,"",IF(17<=Inputs!$C$11,"Senior interest",IF(17=Inputs!$C$11+1,"Senior exit fee ("&TEXT(Inputs!$C$36,"0.00%")&")",IF(17=Inputs!$C$11+2,"Senior loan repaid","")))) -> Senior interest | L27: =IF(17<=Inputs!$C$11,M27,IF(17=Inputs!$C$11+1,Inputs!$D$36,IF(17=Inputs!$C$11+2,Inputs!$C$37,""))) -> 14730.308 | M27: =IF(17<=Inputs!$C$11,Inputs!$C$37*Inputs!$C$35*D27/365,IF(17<=Inputs!$C$11+2,0,"")) -> 14730.308 | N27: =IF(17<=Inputs!$C$11+2,0,"") -> 0 | O27: =IF(17<=Inputs!$C$11+1,Inputs!$C$37,IF(17=Inputs!$C$11+2,0,"")) -> 2775000 | P27: =IF(17<=Inputs!$C$11+2,N27-L27,"") -> -14730.308 | R27: =IF(17<=Inputs!$C$11,"Net interest margin",IF(17=Inputs!$C$11+1,"Net exit fee",IF(17=Inputs!$C$11+2,"Redemption in / senior repaid",""))) -> Net interest margin | S27: =IF(17<=Inputs!$C$11+2,L27,"") -> 14730.308 | T27: =IF(17<=Inputs!$C$11,F27-M27,IF(17<=Inputs!$C$11+2,0,"")) -> 11195.034 | U27: =IF(17<=Inputs!$C$11+2,G27,"") -> 25925.342 | V27: =IF(17<=Inputs!$C$11+1,Inputs!$C$38,IF(17=Inputs!$C$11+2,0,"")) -> 925000 | W27: =IF(17<=Inputs!$C$11+2,U27-S27,"") -> 11195.034 | X27: =IF(17<=Inputs!$C$11,IF(OR(Inputs!$C$23="",Inputs!$C$22=""),0,MAX(0,EDATE(Inputs!$C$10,17)-MAX(EDATE(Inputs!$C$10,16),Inputs!$C$23))),"") -> 0 | Z27: =EDATE(Inputs!$C$10,21) -> 46874 | AA27: =IF(21<=Inputs!$C$11,IF(Inputs!$C$24="Serviced Monthly",F31,0)+IF(21=Inputs!$C$11,Inputs!$C$14+Inputs!$D$17,0),0) -> 25089.041 | AB27: =AA27-IF(21<=Inputs!$C$11,M31,0)-IF(21=Inputs!$C$11,Inputs!$C$37+Inputs!$D$36,0) -> 10833.904
A28: =IF(18<=Inputs!$C$11,18,"") -> 18 | B28: =IF(18<=Inputs!$C$11,EDATE(Inputs!$C$10,18),IF(18<=Inputs!$C$11+2,EDATE(Inputs!$C$10,Inputs!$C$11),"")) -> 46784 | C28: =IF(18<=Inputs!$C$11,IF(AND(N(X28)>0,N(X28)<D28),"Interest (rate change)","Interest"),IF(18=Inputs!$C$11+1,"Exit fee ("&TEXT(Inputs!$C$17,"0.00%")&")",IF(18=Inputs!$C$11+2,"Redemption – principal repaid",""))) -> Interest | D28: =IF(18<=Inputs!$C$11,EDATE(Inputs!$C$10,18)-EDATE(Inputs!$C$10,17),"") -> 31 | E28: =IF(18<=Inputs!$C$11+2,0,"") -> 0 | F28: =IF(18<=Inputs!$C$11,Inputs!$C$14*(Inputs!$C$21*(D28-X28)+IF(Inputs!$C$22="",Inputs!$C$21,Inputs!$C$22)*X28)/365,IF(18<=Inputs!$C$11+2,0,"")) -> 25925.342 | G28: =IF(18<=Inputs!$C$11,IF(Inputs!$C$24="Serviced Monthly",F28,0),IF(18=Inputs!$C$11+1,Inputs!$D$17,IF(18=Inputs!$C$11+2,Inputs!$C$14,""))) -> 25925.342 | H28: =IF(18<=Inputs!$C$11+1,Inputs!$C$14,IF(18=Inputs!$C$11+2,0,"")) -> 3700000 | I28: =IF(18<=Inputs!$C$11+2,G28,"") -> 25925.342 | K28: =IF(Inputs!$C$37=0,"",IF(18<=Inputs!$C$11,"Senior interest",IF(18=Inputs!$C$11+1,"Senior exit fee ("&TEXT(Inputs!$C$36,"0.00%")&")",IF(18=Inputs!$C$11+2,"Senior loan repaid","")))) -> Senior interest | L28: =IF(18<=Inputs!$C$11,M28,IF(18=Inputs!$C$11+1,Inputs!$D$36,IF(18=Inputs!$C$11+2,Inputs!$C$37,""))) -> 14730.308 | M28: =IF(18<=Inputs!$C$11,Inputs!$C$37*Inputs!$C$35*D28/365,IF(18<=Inputs!$C$11+2,0,"")) -> 14730.308 | N28: =IF(18<=Inputs!$C$11+2,0,"") -> 0 | O28: =IF(18<=Inputs!$C$11+1,Inputs!$C$37,IF(18=Inputs!$C$11+2,0,"")) -> 2775000 | P28: =IF(18<=Inputs!$C$11+2,N28-L28,"") -> -14730.308 | R28: =IF(18<=Inputs!$C$11,"Net interest margin",IF(18=Inputs!$C$11+1,"Net exit fee",IF(18=Inputs!$C$11+2,"Redemption in / senior repaid",""))) -> Net interest margin | S28: =IF(18<=Inputs!$C$11+2,L28,"") -> 14730.308 | T28: =IF(18<=Inputs!$C$11,F28-M28,IF(18<=Inputs!$C$11+2,0,"")) -> 11195.034 | U28: =IF(18<=Inputs!$C$11+2,G28,"") -> 25925.342 | V28: =IF(18<=Inputs!$C$11+1,Inputs!$C$38,IF(18=Inputs!$C$11+2,0,"")) -> 925000 | W28: =IF(18<=Inputs!$C$11+2,U28-S28,"") -> 11195.034 | X28: =IF(18<=Inputs!$C$11,IF(OR(Inputs!$C$23="",Inputs!$C$22=""),0,MAX(0,EDATE(Inputs!$C$10,18)-MAX(EDATE(Inputs!$C$10,17),Inputs!$C$23))),"") -> 0 | Z28: =EDATE(Inputs!$C$10,22) -> 46905 | AA28: =IF(22<=Inputs!$C$11,IF(Inputs!$C$24="Serviced Monthly",F32,0)+IF(22=Inputs!$C$11,Inputs!$C$14+Inputs!$D$17,0),0) -> 25925.342 | AB28: =AA28-IF(22<=Inputs!$C$11,M32,0)-IF(22=Inputs!$C$11,Inputs!$C$37+Inputs!$D$36,0) -> 11195.034
A29: =IF(19<=Inputs!$C$11,19,"") -> 19 | B29: =IF(19<=Inputs!$C$11,EDATE(Inputs!$C$10,19),IF(19<=Inputs!$C$11+2,EDATE(Inputs!$C$10,Inputs!$C$11),"")) -> 46813 | C29: =IF(19<=Inputs!$C$11,IF(AND(N(X29)>0,N(X29)<D29),"Interest (rate change)","Interest"),IF(19=Inputs!$C$11+1,"Exit fee ("&TEXT(Inputs!$C$17,"0.00%")&")",IF(19=Inputs!$C$11+2,"Redemption – principal repaid",""))) -> Interest | D29: =IF(19<=Inputs!$C$11,EDATE(Inputs!$C$10,19)-EDATE(Inputs!$C$10,18),"") -> 29 | E29: =IF(19<=Inputs!$C$11+2,0,"") -> 0 | F29: =IF(19<=Inputs!$C$11,Inputs!$C$14*(Inputs!$C$21*(D29-X29)+IF(Inputs!$C$22="",Inputs!$C$21,Inputs!$C$22)*X29)/365,IF(19<=Inputs!$C$11+2,0,"")) -> 24252.74 | G29: =IF(19<=Inputs!$C$11,IF(Inputs!$C$24="Serviced Monthly",F29,0),IF(19=Inputs!$C$11+1,Inputs!$D$17,IF(19=Inputs!$C$11+2,Inputs!$C$14,""))) -> 24252.74 | H29: =IF(19<=Inputs!$C$11+1,Inputs!$C$14,IF(19=Inputs!$C$11+2,0,"")) -> 3700000 | I29: =IF(19<=Inputs!$C$11+2,G29,"") -> 24252.74 | K29: =IF(Inputs!$C$37=0,"",IF(19<=Inputs!$C$11,"Senior interest",IF(19=Inputs!$C$11+1,"Senior exit fee ("&TEXT(Inputs!$C$36,"0.00%")&")",IF(19=Inputs!$C$11+2,"Senior loan repaid","")))) -> Senior interest | L29: =IF(19<=Inputs!$C$11,M29,IF(19=Inputs!$C$11+1,Inputs!$D$36,IF(19=Inputs!$C$11+2,Inputs!$C$37,""))) -> 13779.966 | M29: =IF(19<=Inputs!$C$11,Inputs!$C$37*Inputs!$C$35*D29/365,IF(19<=Inputs!$C$11+2,0,"")) -> 13779.966 | N29: =IF(19<=Inputs!$C$11+2,0,"") -> 0 | O29: =IF(19<=Inputs!$C$11+1,Inputs!$C$37,IF(19=Inputs!$C$11+2,0,"")) -> 2775000 | P29: =IF(19<=Inputs!$C$11+2,N29-L29,"") -> -13779.966 | R29: =IF(19<=Inputs!$C$11,"Net interest margin",IF(19=Inputs!$C$11+1,"Net exit fee",IF(19=Inputs!$C$11+2,"Redemption in / senior repaid",""))) -> Net interest margin | S29: =IF(19<=Inputs!$C$11+2,L29,"") -> 13779.966 | T29: =IF(19<=Inputs!$C$11,F29-M29,IF(19<=Inputs!$C$11+2,0,"")) -> 10472.774 | U29: =IF(19<=Inputs!$C$11+2,G29,"") -> 24252.74 | V29: =IF(19<=Inputs!$C$11+1,Inputs!$C$38,IF(19=Inputs!$C$11+2,0,"")) -> 925000 | W29: =IF(19<=Inputs!$C$11+2,U29-S29,"") -> 10472.774 | X29: =IF(19<=Inputs!$C$11,IF(OR(Inputs!$C$23="",Inputs!$C$22=""),0,MAX(0,EDATE(Inputs!$C$10,19)-MAX(EDATE(Inputs!$C$10,18),Inputs!$C$23))),"") -> 0 | Z29: =EDATE(Inputs!$C$10,23) -> 46935 | AA29: =IF(23<=Inputs!$C$11,IF(Inputs!$C$24="Serviced Monthly",F33,0)+IF(23=Inputs!$C$11,Inputs!$C$14+Inputs!$D$17,0),0) -> 25089.041 | AB29: =AA29-IF(23<=Inputs!$C$11,M33,0)-IF(23=Inputs!$C$11,Inputs!$C$37+Inputs!$D$36,0) -> 10833.904
A30: =IF(20<=Inputs!$C$11,20,"") -> 20 | B30: =IF(20<=Inputs!$C$11,EDATE(Inputs!$C$10,20),IF(20<=Inputs!$C$11+2,EDATE(Inputs!$C$10,Inputs!$C$11),"")) -> 46844 | C30: =IF(20<=Inputs!$C$11,IF(AND(N(X30)>0,N(X30)<D30),"Interest (rate change)","Interest"),IF(20=Inputs!$C$11+1,"Exit fee ("&TEXT(Inputs!$C$17,"0.00%")&")",IF(20=Inputs!$C$11+2,"Redemption – principal repaid",""))) -> Interest | D30: =IF(20<=Inputs!$C$11,EDATE(Inputs!$C$10,20)-EDATE(Inputs!$C$10,19),"") -> 31 | E30: =IF(20<=Inputs!$C$11+2,0,"") -> 0 | F30: =IF(20<=Inputs!$C$11,Inputs!$C$14*(Inputs!$C$21*(D30-X30)+IF(Inputs!$C$22="",Inputs!$C$21,Inputs!$C$22)*X30)/365,IF(20<=Inputs!$C$11+2,0,"")) -> 25925.342 | G30: =IF(20<=Inputs!$C$11,IF(Inputs!$C$24="Serviced Monthly",F30,0),IF(20=Inputs!$C$11+1,Inputs!$D$17,IF(20=Inputs!$C$11+2,Inputs!$C$14,""))) -> 25925.342 | H30: =IF(20<=Inputs!$C$11+1,Inputs!$C$14,IF(20=Inputs!$C$11+2,0,"")) -> 3700000 | I30: =IF(20<=Inputs!$C$11+2,G30,"") -> 25925.342 | K30: =IF(Inputs!$C$37=0,"",IF(20<=Inputs!$C$11,"Senior interest",IF(20=Inputs!$C$11+1,"Senior exit fee ("&TEXT(Inputs!$C$36,"0.00%")&")",IF(20=Inputs!$C$11+2,"Senior loan repaid","")))) -> Senior interest | L30: =IF(20<=Inputs!$C$11,M30,IF(20=Inputs!$C$11+1,Inputs!$D$36,IF(20=Inputs!$C$11+2,Inputs!$C$37,""))) -> 14730.308 | M30: =IF(20<=Inputs!$C$11,Inputs!$C$37*Inputs!$C$35*D30/365,IF(20<=Inputs!$C$11+2,0,"")) -> 14730.308 | N30: =IF(20<=Inputs!$C$11+2,0,"") -> 0 | O30: =IF(20<=Inputs!$C$11+1,Inputs!$C$37,IF(20=Inputs!$C$11+2,0,"")) -> 2775000 | P30: =IF(20<=Inputs!$C$11+2,N30-L30,"") -> -14730.308 | R30: =IF(20<=Inputs!$C$11,"Net interest margin",IF(20=Inputs!$C$11+1,"Net exit fee",IF(20=Inputs!$C$11+2,"Redemption in / senior repaid",""))) -> Net interest margin | S30: =IF(20<=Inputs!$C$11+2,L30,"") -> 14730.308 | T30: =IF(20<=Inputs!$C$11,F30-M30,IF(20<=Inputs!$C$11+2,0,"")) -> 11195.034 | U30: =IF(20<=Inputs!$C$11+2,G30,"") -> 25925.342 | V30: =IF(20<=Inputs!$C$11+1,Inputs!$C$38,IF(20=Inputs!$C$11+2,0,"")) -> 925000 | W30: =IF(20<=Inputs!$C$11+2,U30-S30,"") -> 11195.034 | X30: =IF(20<=Inputs!$C$11,IF(OR(Inputs!$C$23="",Inputs!$C$22=""),0,MAX(0,EDATE(Inputs!$C$10,20)-MAX(EDATE(Inputs!$C$10,19),Inputs!$C$23))),"") -> 0 | Z30: =EDATE(Inputs!$C$10,24) -> 46966 | AA30: =IF(24<=Inputs!$C$11,IF(Inputs!$C$24="Serviced Monthly",F34,0)+IF(24=Inputs!$C$11,Inputs!$C$14+Inputs!$D$17,0),0) -> 3762925.3 | AB30: =AA30-IF(24<=Inputs!$C$11,M34,0)-IF(24=Inputs!$C$11,Inputs!$C$37+Inputs!$D$36,0) -> 973195.03
A31: =IF(21<=Inputs!$C$11,21,"") -> 21 | B31: =IF(21<=Inputs!$C$11,EDATE(Inputs!$C$10,21),IF(21<=Inputs!$C$11+2,EDATE(Inputs!$C$10,Inputs!$C$11),"")) -> 46874 | C31: =IF(21<=Inputs!$C$11,IF(AND(N(X31)>0,N(X31)<D31),"Interest (rate change)","Interest"),IF(21=Inputs!$C$11+1,"Exit fee ("&TEXT(Inputs!$C$17,"0.00%")&")",IF(21=Inputs!$C$11+2,"Redemption – principal repaid",""))) -> Interest | D31: =IF(21<=Inputs!$C$11,EDATE(Inputs!$C$10,21)-EDATE(Inputs!$C$10,20),"") -> 30 | E31: =IF(21<=Inputs!$C$11+2,0,"") -> 0 | F31: =IF(21<=Inputs!$C$11,Inputs!$C$14*(Inputs!$C$21*(D31-X31)+IF(Inputs!$C$22="",Inputs!$C$21,Inputs!$C$22)*X31)/365,IF(21<=Inputs!$C$11+2,0,"")) -> 25089.041 | G31: =IF(21<=Inputs!$C$11,IF(Inputs!$C$24="Serviced Monthly",F31,0),IF(21=Inputs!$C$11+1,Inputs!$D$17,IF(21=Inputs!$C$11+2,Inputs!$C$14,""))) -> 25089.041 | H31: =IF(21<=Inputs!$C$11+1,Inputs!$C$14,IF(21=Inputs!$C$11+2,0,"")) -> 3700000 | I31: =IF(21<=Inputs!$C$11+2,G31,"") -> 25089.041 | K31: =IF(Inputs!$C$37=0,"",IF(21<=Inputs!$C$11,"Senior interest",IF(21=Inputs!$C$11+1,"Senior exit fee ("&TEXT(Inputs!$C$36,"0.00%")&")",IF(21=Inputs!$C$11+2,"Senior loan repaid","")))) -> Senior interest | L31: =IF(21<=Inputs!$C$11,M31,IF(21=Inputs!$C$11+1,Inputs!$D$36,IF(21=Inputs!$C$11+2,Inputs!$C$37,""))) -> 14255.137 | M31: =IF(21<=Inputs!$C$11,Inputs!$C$37*Inputs!$C$35*D31/365,IF(21<=Inputs!$C$11+2,0,"")) -> 14255.137 | N31: =IF(21<=Inputs!$C$11+2,0,"") -> 0 | O31: =IF(21<=Inputs!$C$11+1,Inputs!$C$37,IF(21=Inputs!$C$11+2,0,"")) -> 2775000 | P31: =IF(21<=Inputs!$C$11+2,N31-L31,"") -> -14255.137 | R31: =IF(21<=Inputs!$C$11,"Net interest margin",IF(21=Inputs!$C$11+1,"Net exit fee",IF(21=Inputs!$C$11+2,"Redemption in / senior repaid",""))) -> Net interest margin | S31: =IF(21<=Inputs!$C$11+2,L31,"") -> 14255.137 | T31: =IF(21<=Inputs!$C$11,F31-M31,IF(21<=Inputs!$C$11+2,0,"")) -> 10833.904 | U31: =IF(21<=Inputs!$C$11+2,G31,"") -> 25089.041 | V31: =IF(21<=Inputs!$C$11+1,Inputs!$C$38,IF(21=Inputs!$C$11+2,0,"")) -> 925000 | W31: =IF(21<=Inputs!$C$11+2,U31-S31,"") -> 10833.904 | X31: =IF(21<=Inputs!$C$11,IF(OR(Inputs!$C$23="",Inputs!$C$22=""),0,MAX(0,EDATE(Inputs!$C$10,21)-MAX(EDATE(Inputs!$C$10,20),Inputs!$C$23))),"") -> 0 | Z31: =EDATE(Inputs!$C$10,25) -> 46997 | AA31: =IF(25<=Inputs!$C$11,IF(Inputs!$C$24="Serviced Monthly",F35,0)+IF(25=Inputs!$C$11,Inputs!$C$14+Inputs!$D$17,0),0) -> 0 | AB31: =AA31-IF(25<=Inputs!$C$11,M35,0)-IF(25=Inputs!$C$11,Inputs!$C$37+Inputs!$D$36,0) -> 0
A32: =IF(22<=Inputs!$C$11,22,"") -> 22 | B32: =IF(22<=Inputs!$C$11,EDATE(Inputs!$C$10,22),IF(22<=Inputs!$C$11+2,EDATE(Inputs!$C$10,Inputs!$C$11),"")) -> 46905 | C32: =IF(22<=Inputs!$C$11,IF(AND(N(X32)>0,N(X32)<D32),"Interest (rate change)","Interest"),IF(22=Inputs!$C$11+1,"Exit fee ("&TEXT(Inputs!$C$17,"0.00%")&")",IF(22=Inputs!$C$11+2,"Redemption – principal repaid",""))) -> Interest | D32: =IF(22<=Inputs!$C$11,EDATE(Inputs!$C$10,22)-EDATE(Inputs!$C$10,21),"") -> 31 | E32: =IF(22<=Inputs!$C$11+2,0,"") -> 0 | F32: =IF(22<=Inputs!$C$11,Inputs!$C$14*(Inputs!$C$21*(D32-X32)+IF(Inputs!$C$22="",Inputs!$C$21,Inputs!$C$22)*X32)/365,IF(22<=Inputs!$C$11+2,0,"")) -> 25925.342 | G32: =IF(22<=Inputs!$C$11,IF(Inputs!$C$24="Serviced Monthly",F32,0),IF(22=Inputs!$C$11+1,Inputs!$D$17,IF(22=Inputs!$C$11+2,Inputs!$C$14,""))) -> 25925.342 | H32: =IF(22<=Inputs!$C$11+1,Inputs!$C$14,IF(22=Inputs!$C$11+2,0,"")) -> 3700000 | I32: =IF(22<=Inputs!$C$11+2,G32,"") -> 25925.342 | K32: =IF(Inputs!$C$37=0,"",IF(22<=Inputs!$C$11,"Senior interest",IF(22=Inputs!$C$11+1,"Senior exit fee ("&TEXT(Inputs!$C$36,"0.00%")&")",IF(22=Inputs!$C$11+2,"Senior loan repaid","")))) -> Senior interest | L32: =IF(22<=Inputs!$C$11,M32,IF(22=Inputs!$C$11+1,Inputs!$D$36,IF(22=Inputs!$C$11+2,Inputs!$C$37,""))) -> 14730.308 | M32: =IF(22<=Inputs!$C$11,Inputs!$C$37*Inputs!$C$35*D32/365,IF(22<=Inputs!$C$11+2,0,"")) -> 14730.308 | N32: =IF(22<=Inputs!$C$11+2,0,"") -> 0 | O32: =IF(22<=Inputs!$C$11+1,Inputs!$C$37,IF(22=Inputs!$C$11+2,0,"")) -> 2775000 | P32: =IF(22<=Inputs!$C$11+2,N32-L32,"") -> -14730.308 | R32: =IF(22<=Inputs!$C$11,"Net interest margin",IF(22=Inputs!$C$11+1,"Net exit fee",IF(22=Inputs!$C$11+2,"Redemption in / senior repaid",""))) -> Net interest margin | S32: =IF(22<=Inputs!$C$11+2,L32,"") -> 14730.308 | T32: =IF(22<=Inputs!$C$11,F32-M32,IF(22<=Inputs!$C$11+2,0,"")) -> 11195.034 | U32: =IF(22<=Inputs!$C$11+2,G32,"") -> 25925.342 | V32: =IF(22<=Inputs!$C$11+1,Inputs!$C$38,IF(22=Inputs!$C$11+2,0,"")) -> 925000 | W32: =IF(22<=Inputs!$C$11+2,U32-S32,"") -> 11195.034 | X32: =IF(22<=Inputs!$C$11,IF(OR(Inputs!$C$23="",Inputs!$C$22=""),0,MAX(0,EDATE(Inputs!$C$10,22)-MAX(EDATE(Inputs!$C$10,21),Inputs!$C$23))),"") -> 0 | Z32: =EDATE(Inputs!$C$10,26) -> 47027 | AA32: =IF(26<=Inputs!$C$11,IF(Inputs!$C$24="Serviced Monthly",F36,0)+IF(26=Inputs!$C$11,Inputs!$C$14+Inputs!$D$17,0),0) -> 0 | AB32: =AA32-IF(26<=Inputs!$C$11,M36,0)-IF(26=Inputs!$C$11,Inputs!$C$37+Inputs!$D$36,0) -> 0
A33: =IF(23<=Inputs!$C$11,23,"") -> 23 | B33: =IF(23<=Inputs!$C$11,EDATE(Inputs!$C$10,23),IF(23<=Inputs!$C$11+2,EDATE(Inputs!$C$10,Inputs!$C$11),"")) -> 46935 | C33: =IF(23<=Inputs!$C$11,IF(AND(N(X33)>0,N(X33)<D33),"Interest (rate change)","Interest"),IF(23=Inputs!$C$11+1,"Exit fee ("&TEXT(Inputs!$C$17,"0.00%")&")",IF(23=Inputs!$C$11+2,"Redemption – principal repaid",""))) -> Interest | D33: =IF(23<=Inputs!$C$11,EDATE(Inputs!$C$10,23)-EDATE(Inputs!$C$10,22),"") -> 30 | E33: =IF(23<=Inputs!$C$11+2,0,"") -> 0 | F33: =IF(23<=Inputs!$C$11,Inputs!$C$14*(Inputs!$C$21*(D33-X33)+IF(Inputs!$C$22="",Inputs!$C$21,Inputs!$C$22)*X33)/365,IF(23<=Inputs!$C$11+2,0,"")) -> 25089.041 | G33: =IF(23<=Inputs!$C$11,IF(Inputs!$C$24="Serviced Monthly",F33,0),IF(23=Inputs!$C$11+1,Inputs!$D$17,IF(23=Inputs!$C$11+2,Inputs!$C$14,""))) -> 25089.041 | H33: =IF(23<=Inputs!$C$11+1,Inputs!$C$14,IF(23=Inputs!$C$11+2,0,"")) -> 3700000 | I33: =IF(23<=Inputs!$C$11+2,G33,"") -> 25089.041 | K33: =IF(Inputs!$C$37=0,"",IF(23<=Inputs!$C$11,"Senior interest",IF(23=Inputs!$C$11+1,"Senior exit fee ("&TEXT(Inputs!$C$36,"0.00%")&")",IF(23=Inputs!$C$11+2,"Senior loan repaid","")))) -> Senior interest | L33: =IF(23<=Inputs!$C$11,M33,IF(23=Inputs!$C$11+1,Inputs!$D$36,IF(23=Inputs!$C$11+2,Inputs!$C$37,""))) -> 14255.137 | M33: =IF(23<=Inputs!$C$11,Inputs!$C$37*Inputs!$C$35*D33/365,IF(23<=Inputs!$C$11+2,0,"")) -> 14255.137 | N33: =IF(23<=Inputs!$C$11+2,0,"") -> 0 | O33: =IF(23<=Inputs!$C$11+1,Inputs!$C$37,IF(23=Inputs!$C$11+2,0,"")) -> 2775000 | P33: =IF(23<=Inputs!$C$11+2,N33-L33,"") -> -14255.137 | R33: =IF(23<=Inputs!$C$11,"Net interest margin",IF(23=Inputs!$C$11+1,"Net exit fee",IF(23=Inputs!$C$11+2,"Redemption in / senior repaid",""))) -> Net interest margin | S33: =IF(23<=Inputs!$C$11+2,L33,"") -> 14255.137 | T33: =IF(23<=Inputs!$C$11,F33-M33,IF(23<=Inputs!$C$11+2,0,"")) -> 10833.904 | U33: =IF(23<=Inputs!$C$11+2,G33,"") -> 25089.041 | V33: =IF(23<=Inputs!$C$11+1,Inputs!$C$38,IF(23=Inputs!$C$11+2,0,"")) -> 925000 | W33: =IF(23<=Inputs!$C$11+2,U33-S33,"") -> 10833.904 | X33: =IF(23<=Inputs!$C$11,IF(OR(Inputs!$C$23="",Inputs!$C$22=""),0,MAX(0,EDATE(Inputs!$C$10,23)-MAX(EDATE(Inputs!$C$10,22),Inputs!$C$23))),"") -> 0 | Z33: =EDATE(Inputs!$C$10,27) -> 47058 | AA33: =IF(27<=Inputs!$C$11,IF(Inputs!$C$24="Serviced Monthly",F37,0)+IF(27=Inputs!$C$11,Inputs!$C$14+Inputs!$D$17,0),0) -> 0 | AB33: =AA33-IF(27<=Inputs!$C$11,M37,0)-IF(27=Inputs!$C$11,Inputs!$C$37+Inputs!$D$36,0) -> 0
A34: =IF(24<=Inputs!$C$11,24,"") -> 24 | B34: =IF(24<=Inputs!$C$11,EDATE(Inputs!$C$10,24),IF(24<=Inputs!$C$11+2,EDATE(Inputs!$C$10,Inputs!$C$11),"")) -> 46966 | C34: =IF(24<=Inputs!$C$11,IF(AND(N(X34)>0,N(X34)<D34),"Interest (rate change)","Interest"),IF(24=Inputs!$C$11+1,"Exit fee ("&TEXT(Inputs!$C$17,"0.00%")&")",IF(24=Inputs!$C$11+2,"Redemption – principal repaid",""))) -> Interest | D34: =IF(24<=Inputs!$C$11,EDATE(Inputs!$C$10,24)-EDATE(Inputs!$C$10,23),"") -> 31 | E34: =IF(24<=Inputs!$C$11+2,0,"") -> 0 | F34: =IF(24<=Inputs!$C$11,Inputs!$C$14*(Inputs!$C$21*(D34-X34)+IF(Inputs!$C$22="",Inputs!$C$21,Inputs!$C$22)*X34)/365,IF(24<=Inputs!$C$11+2,0,"")) -> 25925.342 | G34: =IF(24<=Inputs!$C$11,IF(Inputs!$C$24="Serviced Monthly",F34,0),IF(24=Inputs!$C$11+1,Inputs!$D$17,IF(24=Inputs!$C$11+2,Inputs!$C$14,""))) -> 25925.342 | H34: =IF(24<=Inputs!$C$11+1,Inputs!$C$14,IF(24=Inputs!$C$11+2,0,"")) -> 3700000 | I34: =IF(24<=Inputs!$C$11+2,G34,"") -> 25925.342 | K34: =IF(Inputs!$C$37=0,"",IF(24<=Inputs!$C$11,"Senior interest",IF(24=Inputs!$C$11+1,"Senior exit fee ("&TEXT(Inputs!$C$36,"0.00%")&")",IF(24=Inputs!$C$11+2,"Senior loan repaid","")))) -> Senior interest | L34: =IF(24<=Inputs!$C$11,M34,IF(24=Inputs!$C$11+1,Inputs!$D$36,IF(24=Inputs!$C$11+2,Inputs!$C$37,""))) -> 14730.308 | M34: =IF(24<=Inputs!$C$11,Inputs!$C$37*Inputs!$C$35*D34/365,IF(24<=Inputs!$C$11+2,0,"")) -> 14730.308 | N34: =IF(24<=Inputs!$C$11+2,0,"") -> 0 | O34: =IF(24<=Inputs!$C$11+1,Inputs!$C$37,IF(24=Inputs!$C$11+2,0,"")) -> 2775000 | P34: =IF(24<=Inputs!$C$11+2,N34-L34,"") -> -14730.308 | R34: =IF(24<=Inputs!$C$11,"Net interest margin",IF(24=Inputs!$C$11+1,"Net exit fee",IF(24=Inputs!$C$11+2,"Redemption in / senior repaid",""))) -> Net interest margin | S34: =IF(24<=Inputs!$C$11+2,L34,"") -> 14730.308 | T34: =IF(24<=Inputs!$C$11,F34-M34,IF(24<=Inputs!$C$11+2,0,"")) -> 11195.034 | U34: =IF(24<=Inputs!$C$11+2,G34,"") -> 25925.342 | V34: =IF(24<=Inputs!$C$11+1,Inputs!$C$38,IF(24=Inputs!$C$11+2,0,"")) -> 925000 | W34: =IF(24<=Inputs!$C$11+2,U34-S34,"") -> 11195.034 | X34: =IF(24<=Inputs!$C$11,IF(OR(Inputs!$C$23="",Inputs!$C$22=""),0,MAX(0,EDATE(Inputs!$C$10,24)-MAX(EDATE(Inputs!$C$10,23),Inputs!$C$23))),"") -> 0 | Z34: =EDATE(Inputs!$C$10,28) -> 47088 | AA34: =IF(28<=Inputs!$C$11,IF(Inputs!$C$24="Serviced Monthly",F38,0)+IF(28=Inputs!$C$11,Inputs!$C$14+Inputs!$D$17,0),0) -> 0 | AB34: =AA34-IF(28<=Inputs!$C$11,M38,0)-IF(28=Inputs!$C$11,Inputs!$C$37+Inputs!$D$36,0) -> 0
A35: =IF(25<=Inputs!$C$11,25,"") | B35: =IF(25<=Inputs!$C$11,EDATE(Inputs!$C$10,25),IF(25<=Inputs!$C$11+2,EDATE(Inputs!$C$10,Inputs!$C$11),"")) -> 46966 | C35: =IF(25<=Inputs!$C$11,IF(AND(N(X35)>0,N(X35)<D35),"Interest (rate change)","Interest"),IF(25=Inputs!$C$11+1,"Exit fee ("&TEXT(Inputs!$C$17,"0.00%")&")",IF(25=Inputs!$C$11+2,"Redemption – principal repaid",""))) -> Exit fee (1.00%) | D35: =IF(25<=Inputs!$C$11,EDATE(Inputs!$C$10,25)-EDATE(Inputs!$C$10,24),"") | E35: =IF(25<=Inputs!$C$11+2,0,"") -> 0 | F35: =IF(25<=Inputs!$C$11,Inputs!$C$14*(Inputs!$C$21*(D35-X35)+IF(Inputs!$C$22="",Inputs!$C$21,Inputs!$C$22)*X35)/365,IF(25<=Inputs!$C$11+2,0,"")) -> 0 | G35: =IF(25<=Inputs!$C$11,IF(Inputs!$C$24="Serviced Monthly",F35,0),IF(25=Inputs!$C$11+1,Inputs!$D$17,IF(25=Inputs!$C$11+2,Inputs!$C$14,""))) -> 37000 | H35: =IF(25<=Inputs!$C$11+1,Inputs!$C$14,IF(25=Inputs!$C$11+2,0,"")) -> 3700000 | I35: =IF(25<=Inputs!$C$11+2,G35,"") -> 37000 | K35: =IF(Inputs!$C$37=0,"",IF(25<=Inputs!$C$11,"Senior interest",IF(25=Inputs!$C$11+1,"Senior exit fee ("&TEXT(Inputs!$C$36,"0.00%")&")",IF(25=Inputs!$C$11+2,"Senior loan repaid","")))) -> Senior exit fee (0.00%) | L35: =IF(25<=Inputs!$C$11,M35,IF(25=Inputs!$C$11+1,Inputs!$D$36,IF(25=Inputs!$C$11+2,Inputs!$C$37,""))) -> 0 | M35: =IF(25<=Inputs!$C$11,Inputs!$C$37*Inputs!$C$35*D35/365,IF(25<=Inputs!$C$11+2,0,"")) -> 0 | N35: =IF(25<=Inputs!$C$11+2,0,"") -> 0 | O35: =IF(25<=Inputs!$C$11+1,Inputs!$C$37,IF(25=Inputs!$C$11+2,0,"")) -> 2775000 | P35: =IF(25<=Inputs!$C$11+2,N35-L35,"") -> 0 | R35: =IF(25<=Inputs!$C$11,"Net interest margin",IF(25=Inputs!$C$11+1,"Net exit fee",IF(25=Inputs!$C$11+2,"Redemption in / senior repaid",""))) -> Net exit fee | S35: =IF(25<=Inputs!$C$11+2,L35,"") -> 0 | T35: =IF(25<=Inputs!$C$11,F35-M35,IF(25<=Inputs!$C$11+2,0,"")) -> 0 | U35: =IF(25<=Inputs!$C$11+2,G35,"") -> 37000 | V35: =IF(25<=Inputs!$C$11+1,Inputs!$C$38,IF(25=Inputs!$C$11+2,0,"")) -> 925000 | W35: =IF(25<=Inputs!$C$11+2,U35-S35,"") -> 37000 | X35: =IF(25<=Inputs!$C$11,IF(OR(Inputs!$C$23="",Inputs!$C$22=""),0,MAX(0,EDATE(Inputs!$C$10,25)-MAX(EDATE(Inputs!$C$10,24),Inputs!$C$23))),"") | Z35: =EDATE(Inputs!$C$10,29) -> 47119 | AA35: =IF(29<=Inputs!$C$11,IF(Inputs!$C$24="Serviced Monthly",F39,0)+IF(29=Inputs!$C$11,Inputs!$C$14+Inputs!$D$17,0),0) -> 0 | AB35: =AA35-IF(29<=Inputs!$C$11,M39,0)-IF(29=Inputs!$C$11,Inputs!$C$37+Inputs!$D$36,0) -> 0
A36: =IF(26<=Inputs!$C$11,26,"") | B36: =IF(26<=Inputs!$C$11,EDATE(Inputs!$C$10,26),IF(26<=Inputs!$C$11+2,EDATE(Inputs!$C$10,Inputs!$C$11),"")) -> 46966 | C36: =IF(26<=Inputs!$C$11,IF(AND(N(X36)>0,N(X36)<D36),"Interest (rate change)","Interest"),IF(26=Inputs!$C$11+1,"Exit fee ("&TEXT(Inputs!$C$17,"0.00%")&")",IF(26=Inputs!$C$11+2,"Redemption – principal repaid",""))) -> Redemption – principal repaid | D36: =IF(26<=Inputs!$C$11,EDATE(Inputs!$C$10,26)-EDATE(Inputs!$C$10,25),"") | E36: =IF(26<=Inputs!$C$11+2,0,"") -> 0 | F36: =IF(26<=Inputs!$C$11,Inputs!$C$14*(Inputs!$C$21*(D36-X36)+IF(Inputs!$C$22="",Inputs!$C$21,Inputs!$C$22)*X36)/365,IF(26<=Inputs!$C$11+2,0,"")) -> 0 | G36: =IF(26<=Inputs!$C$11,IF(Inputs!$C$24="Serviced Monthly",F36,0),IF(26=Inputs!$C$11+1,Inputs!$D$17,IF(26=Inputs!$C$11+2,Inputs!$C$14,""))) -> 3700000 | H36: =IF(26<=Inputs!$C$11+1,Inputs!$C$14,IF(26=Inputs!$C$11+2,0,"")) -> 0 | I36: =IF(26<=Inputs!$C$11+2,G36,"") -> 3700000 | K36: =IF(Inputs!$C$37=0,"",IF(26<=Inputs!$C$11,"Senior interest",IF(26=Inputs!$C$11+1,"Senior exit fee ("&TEXT(Inputs!$C$36,"0.00%")&")",IF(26=Inputs!$C$11+2,"Senior loan repaid","")))) -> Senior loan repaid | L36: =IF(26<=Inputs!$C$11,M36,IF(26=Inputs!$C$11+1,Inputs!$D$36,IF(26=Inputs!$C$11+2,Inputs!$C$37,""))) -> 2775000 | M36: =IF(26<=Inputs!$C$11,Inputs!$C$37*Inputs!$C$35*D36/365,IF(26<=Inputs!$C$11+2,0,"")) -> 0 | N36: =IF(26<=Inputs!$C$11+2,0,"") -> 0 | O36: =IF(26<=Inputs!$C$11+1,Inputs!$C$37,IF(26=Inputs!$C$11+2,0,"")) -> 0 | P36: =IF(26<=Inputs!$C$11+2,N36-L36,"") -> -2775000 | R36: =IF(26<=Inputs!$C$11,"Net interest margin",IF(26=Inputs!$C$11+1,"Net exit fee",IF(26=Inputs!$C$11+2,"Redemption in / senior repaid",""))) -> Redemption in / senior repaid | S36: =IF(26<=Inputs!$C$11+2,L36,"") -> 2775000 | T36: =IF(26<=Inputs!$C$11,F36-M36,IF(26<=Inputs!$C$11+2,0,"")) -> 0 | U36: =IF(26<=Inputs!$C$11+2,G36,"") -> 3700000 | V36: =IF(26<=Inputs!$C$11+1,Inputs!$C$38,IF(26=Inputs!$C$11+2,0,"")) -> 0 | W36: =IF(26<=Inputs!$C$11+2,U36-S36,"") -> 925000 | X36: =IF(26<=Inputs!$C$11,IF(OR(Inputs!$C$23="",Inputs!$C$22=""),0,MAX(0,EDATE(Inputs!$C$10,26)-MAX(EDATE(Inputs!$C$10,25),Inputs!$C$23))),"") | Z36: =EDATE(Inputs!$C$10,30) -> 47150 | AA36: =IF(30<=Inputs!$C$11,IF(Inputs!$C$24="Serviced Monthly",F40,0)+IF(30=Inputs!$C$11,Inputs!$C$14+Inputs!$D$17,0),0) -> 0 | AB36: =AA36-IF(30<=Inputs!$C$11,M40,0)-IF(30=Inputs!$C$11,Inputs!$C$37+Inputs!$D$36,0) -> 0
A37: =IF(27<=Inputs!$C$11,27,"") | B37: =IF(27<=Inputs!$C$11,EDATE(Inputs!$C$10,27),IF(27<=Inputs!$C$11+2,EDATE(Inputs!$C$10,Inputs!$C$11),"")) | C37: =IF(27<=Inputs!$C$11,IF(AND(N(X37)>0,N(X37)<D37),"Interest (rate change)","Interest"),IF(27=Inputs!$C$11+1,"Exit fee ("&TEXT(Inputs!$C$17,"0.00%")&")",IF(27=Inputs!$C$11+2,"Redemption – principal repaid",""))) | D37: =IF(27<=Inputs!$C$11,EDATE(Inputs!$C$10,27)-EDATE(Inputs!$C$10,26),"") | E37: =IF(27<=Inputs!$C$11+2,0,"") | F37: =IF(27<=Inputs!$C$11,Inputs!$C$14*(Inputs!$C$21*(D37-X37)+IF(Inputs!$C$22="",Inputs!$C$21,Inputs!$C$22)*X37)/365,IF(27<=Inputs!$C$11+2,0,"")) | G37: =IF(27<=Inputs!$C$11,IF(Inputs!$C$24="Serviced Monthly",F37,0),IF(27=Inputs!$C$11+1,Inputs!$D$17,IF(27=Inputs!$C$11+2,Inputs!$C$14,""))) | H37: =IF(27<=Inputs!$C$11+1,Inputs!$C$14,IF(27=Inputs!$C$11+2,0,"")) | I37: =IF(27<=Inputs!$C$11+2,G37,"") | K37: =IF(Inputs!$C$37=0,"",IF(27<=Inputs!$C$11,"Senior interest",IF(27=Inputs!$C$11+1,"Senior exit fee ("&TEXT(Inputs!$C$36,"0.00%")&")",IF(27=Inputs!$C$11+2,"Senior loan repaid","")))) | L37: =IF(27<=Inputs!$C$11,M37,IF(27=Inputs!$C$11+1,Inputs!$D$36,IF(27=Inputs!$C$11+2,Inputs!$C$37,""))) | M37: =IF(27<=Inputs!$C$11,Inputs!$C$37*Inputs!$C$35*D37/365,IF(27<=Inputs!$C$11+2,0,"")) | N37: =IF(27<=Inputs!$C$11+2,0,"") | O37: =IF(27<=Inputs!$C$11+1,Inputs!$C$37,IF(27=Inputs!$C$11+2,0,"")) | P37: =IF(27<=Inputs!$C$11+2,N37-L37,"") | R37: =IF(27<=Inputs!$C$11,"Net interest margin",IF(27=Inputs!$C$11+1,"Net exit fee",IF(27=Inputs!$C$11+2,"Redemption in / senior repaid",""))) | S37: =IF(27<=Inputs!$C$11+2,L37,"") | T37: =IF(27<=Inputs!$C$11,F37-M37,IF(27<=Inputs!$C$11+2,0,"")) | U37: =IF(27<=Inputs!$C$11+2,G37,"") | V37: =IF(27<=Inputs!$C$11+1,Inputs!$C$38,IF(27=Inputs!$C$11+2,0,"")) | W37: =IF(27<=Inputs!$C$11+2,U37-S37,"") | X37: =IF(27<=Inputs!$C$11,IF(OR(Inputs!$C$23="",Inputs!$C$22=""),0,MAX(0,EDATE(Inputs!$C$10,27)-MAX(EDATE(Inputs!$C$10,26),Inputs!$C$23))),"") | Z37: =EDATE(Inputs!$C$10,31) -> 47178 | AA37: =IF(31<=Inputs!$C$11,IF(Inputs!$C$24="Serviced Monthly",F41,0)+IF(31=Inputs!$C$11,Inputs!$C$14+Inputs!$D$17,0),0) -> 0 | AB37: =AA37-IF(31<=Inputs!$C$11,M41,0)-IF(31=Inputs!$C$11,Inputs!$C$37+Inputs!$D$36,0) -> 0
A38: =IF(28<=Inputs!$C$11,28,"") | B38: =IF(28<=Inputs!$C$11,EDATE(Inputs!$C$10,28),IF(28<=Inputs!$C$11+2,EDATE(Inputs!$C$10,Inputs!$C$11),"")) | C38: =IF(28<=Inputs!$C$11,IF(AND(N(X38)>0,N(X38)<D38),"Interest (rate change)","Interest"),IF(28=Inputs!$C$11+1,"Exit fee ("&TEXT(Inputs!$C$17,"0.00%")&")",IF(28=Inputs!$C$11+2,"Redemption – principal repaid",""))) | D38: =IF(28<=Inputs!$C$11,EDATE(Inputs!$C$10,28)-EDATE(Inputs!$C$10,27),"") | E38: =IF(28<=Inputs!$C$11+2,0,"") | F38: =IF(28<=Inputs!$C$11,Inputs!$C$14*(Inputs!$C$21*(D38-X38)+IF(Inputs!$C$22="",Inputs!$C$21,Inputs!$C$22)*X38)/365,IF(28<=Inputs!$C$11+2,0,"")) | G38: =IF(28<=Inputs!$C$11,IF(Inputs!$C$24="Serviced Monthly",F38,0),IF(28=Inputs!$C$11+1,Inputs!$D$17,IF(28=Inputs!$C$11+2,Inputs!$C$14,""))) | H38: =IF(28<=Inputs!$C$11+1,Inputs!$C$14,IF(28=Inputs!$C$11+2,0,"")) | I38: =IF(28<=Inputs!$C$11+2,G38,"") | K38: =IF(Inputs!$C$37=0,"",IF(28<=Inputs!$C$11,"Senior interest",IF(28=Inputs!$C$11+1,"Senior exit fee ("&TEXT(Inputs!$C$36,"0.00%")&")",IF(28=Inputs!$C$11+2,"Senior loan repaid","")))) | L38: =IF(28<=Inputs!$C$11,M38,IF(28=Inputs!$C$11+1,Inputs!$D$36,IF(28=Inputs!$C$11+2,Inputs!$C$37,""))) | M38: =IF(28<=Inputs!$C$11,Inputs!$C$37*Inputs!$C$35*D38/365,IF(28<=Inputs!$C$11+2,0,"")) | N38: =IF(28<=Inputs!$C$11+2,0,"") | O38: =IF(28<=Inputs!$C$11+1,Inputs!$C$37,IF(28=Inputs!$C$11+2,0,"")) | P38: =IF(28<=Inputs!$C$11+2,N38-L38,"") | R38: =IF(28<=Inputs!$C$11,"Net interest margin",IF(28=Inputs!$C$11+1,"Net exit fee",IF(28=Inputs!$C$11+2,"Redemption in / senior repaid",""))) | S38: =IF(28<=Inputs!$C$11+2,L38,"") | T38: =IF(28<=Inputs!$C$11,F38-M38,IF(28<=Inputs!$C$11+2,0,"")) | U38: =IF(28<=Inputs!$C$11+2,G38,"") | V38: =IF(28<=Inputs!$C$11+1,Inputs!$C$38,IF(28=Inputs!$C$11+2,0,"")) | W38: =IF(28<=Inputs!$C$11+2,U38-S38,"") | X38: =IF(28<=Inputs!$C$11,IF(OR(Inputs!$C$23="",Inputs!$C$22=""),0,MAX(0,EDATE(Inputs!$C$10,28)-MAX(EDATE(Inputs!$C$10,27),Inputs!$C$23))),"") | Z38: =EDATE(Inputs!$C$10,32) -> 47209 | AA38: =IF(32<=Inputs!$C$11,IF(Inputs!$C$24="Serviced Monthly",F42,0)+IF(32=Inputs!$C$11,Inputs!$C$14+Inputs!$D$17,0),0) -> 0 | AB38: =AA38-IF(32<=Inputs!$C$11,M42,0)-IF(32=Inputs!$C$11,Inputs!$C$37+Inputs!$D$36,0) -> 0
A39: =IF(29<=Inputs!$C$11,29,"") | B39: =IF(29<=Inputs!$C$11,EDATE(Inputs!$C$10,29),IF(29<=Inputs!$C$11+2,EDATE(Inputs!$C$10,Inputs!$C$11),"")) | C39: =IF(29<=Inputs!$C$11,IF(AND(N(X39)>0,N(X39)<D39),"Interest (rate change)","Interest"),IF(29=Inputs!$C$11+1,"Exit fee ("&TEXT(Inputs!$C$17,"0.00%")&")",IF(29=Inputs!$C$11+2,"Redemption – principal repaid",""))) | D39: =IF(29<=Inputs!$C$11,EDATE(Inputs!$C$10,29)-EDATE(Inputs!$C$10,28),"") | E39: =IF(29<=Inputs!$C$11+2,0,"") | F39: =IF(29<=Inputs!$C$11,Inputs!$C$14*(Inputs!$C$21*(D39-X39)+IF(Inputs!$C$22="",Inputs!$C$21,Inputs!$C$22)*X39)/365,IF(29<=Inputs!$C$11+2,0,"")) | G39: =IF(29<=Inputs!$C$11,IF(Inputs!$C$24="Serviced Monthly",F39,0),IF(29=Inputs!$C$11+1,Inputs!$D$17,IF(29=Inputs!$C$11+2,Inputs!$C$14,""))) | H39: =IF(29<=Inputs!$C$11+1,Inputs!$C$14,IF(29=Inputs!$C$11+2,0,"")) | I39: =IF(29<=Inputs!$C$11+2,G39,"") | K39: =IF(Inputs!$C$37=0,"",IF(29<=Inputs!$C$11,"Senior interest",IF(29=Inputs!$C$11+1,"Senior exit fee ("&TEXT(Inputs!$C$36,"0.00%")&")",IF(29=Inputs!$C$11+2,"Senior loan repaid","")))) | L39: =IF(29<=Inputs!$C$11,M39,IF(29=Inputs!$C$11+1,Inputs!$D$36,IF(29=Inputs!$C$11+2,Inputs!$C$37,""))) | M39: =IF(29<=Inputs!$C$11,Inputs!$C$37*Inputs!$C$35*D39/365,IF(29<=Inputs!$C$11+2,0,"")) | N39: =IF(29<=Inputs!$C$11+2,0,"") | O39: =IF(29<=Inputs!$C$11+1,Inputs!$C$37,IF(29=Inputs!$C$11+2,0,"")) | P39: =IF(29<=Inputs!$C$11+2,N39-L39,"") | R39: =IF(29<=Inputs!$C$11,"Net interest margin",IF(29=Inputs!$C$11+1,"Net exit fee",IF(29=Inputs!$C$11+2,"Redemption in / senior repaid",""))) | S39: =IF(29<=Inputs!$C$11+2,L39,"") | T39: =IF(29<=Inputs!$C$11,F39-M39,IF(29<=Inputs!$C$11+2,0,"")) | U39: =IF(29<=Inputs!$C$11+2,G39,"") | V39: =IF(29<=Inputs!$C$11+1,Inputs!$C$38,IF(29=Inputs!$C$11+2,0,"")) | W39: =IF(29<=Inputs!$C$11+2,U39-S39,"") | X39: =IF(29<=Inputs!$C$11,IF(OR(Inputs!$C$23="",Inputs!$C$22=""),0,MAX(0,EDATE(Inputs!$C$10,29)-MAX(EDATE(Inputs!$C$10,28),Inputs!$C$23))),"") | Z39: =EDATE(Inputs!$C$10,33) -> 47239 | AA39: =IF(33<=Inputs!$C$11,IF(Inputs!$C$24="Serviced Monthly",F43,0)+IF(33=Inputs!$C$11,Inputs!$C$14+Inputs!$D$17,0),0) -> 0 | AB39: =AA39-IF(33<=Inputs!$C$11,M43,0)-IF(33=Inputs!$C$11,Inputs!$C$37+Inputs!$D$36,0) -> 0
A40: =IF(30<=Inputs!$C$11,30,"") | B40: =IF(30<=Inputs!$C$11,EDATE(Inputs!$C$10,30),IF(30<=Inputs!$C$11+2,EDATE(Inputs!$C$10,Inputs!$C$11),"")) | C40: =IF(30<=Inputs!$C$11,IF(AND(N(X40)>0,N(X40)<D40),"Interest (rate change)","Interest"),IF(30=Inputs!$C$11+1,"Exit fee ("&TEXT(Inputs!$C$17,"0.00%")&")",IF(30=Inputs!$C$11+2,"Redemption – principal repaid",""))) | D40: =IF(30<=Inputs!$C$11,EDATE(Inputs!$C$10,30)-EDATE(Inputs!$C$10,29),"") | E40: =IF(30<=Inputs!$C$11+2,0,"") | F40: =IF(30<=Inputs!$C$11,Inputs!$C$14*(Inputs!$C$21*(D40-X40)+IF(Inputs!$C$22="",Inputs!$C$21,Inputs!$C$22)*X40)/365,IF(30<=Inputs!$C$11+2,0,"")) | G40: =IF(30<=Inputs!$C$11,IF(Inputs!$C$24="Serviced Monthly",F40,0),IF(30=Inputs!$C$11+1,Inputs!$D$17,IF(30=Inputs!$C$11+2,Inputs!$C$14,""))) | H40: =IF(30<=Inputs!$C$11+1,Inputs!$C$14,IF(30=Inputs!$C$11+2,0,"")) | I40: =IF(30<=Inputs!$C$11+2,G40,"") | K40: =IF(Inputs!$C$37=0,"",IF(30<=Inputs!$C$11,"Senior interest",IF(30=Inputs!$C$11+1,"Senior exit fee ("&TEXT(Inputs!$C$36,"0.00%")&")",IF(30=Inputs!$C$11+2,"Senior loan repaid","")))) | L40: =IF(30<=Inputs!$C$11,M40,IF(30=Inputs!$C$11+1,Inputs!$D$36,IF(30=Inputs!$C$11+2,Inputs!$C$37,""))) | M40: =IF(30<=Inputs!$C$11,Inputs!$C$37*Inputs!$C$35*D40/365,IF(30<=Inputs!$C$11+2,0,"")) | N40: =IF(30<=Inputs!$C$11+2,0,"") | O40: =IF(30<=Inputs!$C$11+1,Inputs!$C$37,IF(30=Inputs!$C$11+2,0,"")) | P40: =IF(30<=Inputs!$C$11+2,N40-L40,"") | R40: =IF(30<=Inputs!$C$11,"Net interest margin",IF(30=Inputs!$C$11+1,"Net exit fee",IF(30=Inputs!$C$11+2,"Redemption in / senior repaid",""))) | S40: =IF(30<=Inputs!$C$11+2,L40,"") | T40: =IF(30<=Inputs!$C$11,F40-M40,IF(30<=Inputs!$C$11+2,0,"")) | U40: =IF(30<=Inputs!$C$11+2,G40,"") | V40: =IF(30<=Inputs!$C$11+1,Inputs!$C$38,IF(30=Inputs!$C$11+2,0,"")) | W40: =IF(30<=Inputs!$C$11+2,U40-S40,"") | X40: =IF(30<=Inputs!$C$11,IF(OR(Inputs!$C$23="",Inputs!$C$22=""),0,MAX(0,EDATE(Inputs!$C$10,30)-MAX(EDATE(Inputs!$C$10,29),Inputs!$C$23))),"") | Z40: =EDATE(Inputs!$C$10,34) -> 47270 | AA40: =IF(34<=Inputs!$C$11,IF(Inputs!$C$24="Serviced Monthly",F44,0)+IF(34=Inputs!$C$11,Inputs!$C$14+Inputs!$D$17,0),0) -> 0 | AB40: =AA40-IF(34<=Inputs!$C$11,M44,0)-IF(34=Inputs!$C$11,Inputs!$C$37+Inputs!$D$36,0) -> 0
A41: =IF(31<=Inputs!$C$11,31,"") | B41: =IF(31<=Inputs!$C$11,EDATE(Inputs!$C$10,31),IF(31<=Inputs!$C$11+2,EDATE(Inputs!$C$10,Inputs!$C$11),"")) | C41: =IF(31<=Inputs!$C$11,IF(AND(N(X41)>0,N(X41)<D41),"Interest (rate change)","Interest"),IF(31=Inputs!$C$11+1,"Exit fee ("&TEXT(Inputs!$C$17,"0.00%")&")",IF(31=Inputs!$C$11+2,"Redemption – principal repaid",""))) | D41: =IF(31<=Inputs!$C$11,EDATE(Inputs!$C$10,31)-EDATE(Inputs!$C$10,30),"") | E41: =IF(31<=Inputs!$C$11+2,0,"") | F41: =IF(31<=Inputs!$C$11,Inputs!$C$14*(Inputs!$C$21*(D41-X41)+IF(Inputs!$C$22="",Inputs!$C$21,Inputs!$C$22)*X41)/365,IF(31<=Inputs!$C$11+2,0,"")) | G41: =IF(31<=Inputs!$C$11,IF(Inputs!$C$24="Serviced Monthly",F41,0),IF(31=Inputs!$C$11+1,Inputs!$D$17,IF(31=Inputs!$C$11+2,Inputs!$C$14,""))) | H41: =IF(31<=Inputs!$C$11+1,Inputs!$C$14,IF(31=Inputs!$C$11+2,0,"")) | I41: =IF(31<=Inputs!$C$11+2,G41,"") | K41: =IF(Inputs!$C$37=0,"",IF(31<=Inputs!$C$11,"Senior interest",IF(31=Inputs!$C$11+1,"Senior exit fee ("&TEXT(Inputs!$C$36,"0.00%")&")",IF(31=Inputs!$C$11+2,"Senior loan repaid","")))) | L41: =IF(31<=Inputs!$C$11,M41,IF(31=Inputs!$C$11+1,Inputs!$D$36,IF(31=Inputs!$C$11+2,Inputs!$C$37,""))) | M41: =IF(31<=Inputs!$C$11,Inputs!$C$37*Inputs!$C$35*D41/365,IF(31<=Inputs!$C$11+2,0,"")) | N41: =IF(31<=Inputs!$C$11+2,0,"") | O41: =IF(31<=Inputs!$C$11+1,Inputs!$C$37,IF(31=Inputs!$C$11+2,0,"")) | P41: =IF(31<=Inputs!$C$11+2,N41-L41,"") | R41: =IF(31<=Inputs!$C$11,"Net interest margin",IF(31=Inputs!$C$11+1,"Net exit fee",IF(31=Inputs!$C$11+2,"Redemption in / senior repaid",""))) | S41: =IF(31<=Inputs!$C$11+2,L41,"") | T41: =IF(31<=Inputs!$C$11,F41-M41,IF(31<=Inputs!$C$11+2,0,"")) | U41: =IF(31<=Inputs!$C$11+2,G41,"") | V41: =IF(31<=Inputs!$C$11+1,Inputs!$C$38,IF(31=Inputs!$C$11+2,0,"")) | W41: =IF(31<=Inputs!$C$11+2,U41-S41,"") | X41: =IF(31<=Inputs!$C$11,IF(OR(Inputs!$C$23="",Inputs!$C$22=""),0,MAX(0,EDATE(Inputs!$C$10,31)-MAX(EDATE(Inputs!$C$10,30),Inputs!$C$23))),"") | Z41: =EDATE(Inputs!$C$10,35) -> 47300 | AA41: =IF(35<=Inputs!$C$11,IF(Inputs!$C$24="Serviced Monthly",F45,0)+IF(35=Inputs!$C$11,Inputs!$C$14+Inputs!$D$17,0),0) -> 0 | AB41: =AA41-IF(35<=Inputs!$C$11,M45,0)-IF(35=Inputs!$C$11,Inputs!$C$37+Inputs!$D$36,0) -> 0
A42: =IF(32<=Inputs!$C$11,32,"") | B42: =IF(32<=Inputs!$C$11,EDATE(Inputs!$C$10,32),IF(32<=Inputs!$C$11+2,EDATE(Inputs!$C$10,Inputs!$C$11),"")) | C42: =IF(32<=Inputs!$C$11,IF(AND(N(X42)>0,N(X42)<D42),"Interest (rate change)","Interest"),IF(32=Inputs!$C$11+1,"Exit fee ("&TEXT(Inputs!$C$17,"0.00%")&")",IF(32=Inputs!$C$11+2,"Redemption – principal repaid",""))) | D42: =IF(32<=Inputs!$C$11,EDATE(Inputs!$C$10,32)-EDATE(Inputs!$C$10,31),"") | E42: =IF(32<=Inputs!$C$11+2,0,"") | F42: =IF(32<=Inputs!$C$11,Inputs!$C$14*(Inputs!$C$21*(D42-X42)+IF(Inputs!$C$22="",Inputs!$C$21,Inputs!$C$22)*X42)/365,IF(32<=Inputs!$C$11+2,0,"")) | G42: =IF(32<=Inputs!$C$11,IF(Inputs!$C$24="Serviced Monthly",F42,0),IF(32=Inputs!$C$11+1,Inputs!$D$17,IF(32=Inputs!$C$11+2,Inputs!$C$14,""))) | H42: =IF(32<=Inputs!$C$11+1,Inputs!$C$14,IF(32=Inputs!$C$11+2,0,"")) | I42: =IF(32<=Inputs!$C$11+2,G42,"") | K42: =IF(Inputs!$C$37=0,"",IF(32<=Inputs!$C$11,"Senior interest",IF(32=Inputs!$C$11+1,"Senior exit fee ("&TEXT(Inputs!$C$36,"0.00%")&")",IF(32=Inputs!$C$11+2,"Senior loan repaid","")))) | L42: =IF(32<=Inputs!$C$11,M42,IF(32=Inputs!$C$11+1,Inputs!$D$36,IF(32=Inputs!$C$11+2,Inputs!$C$37,""))) | M42: =IF(32<=Inputs!$C$11,Inputs!$C$37*Inputs!$C$35*D42/365,IF(32<=Inputs!$C$11+2,0,"")) | N42: =IF(32<=Inputs!$C$11+2,0,"") | O42: =IF(32<=Inputs!$C$11+1,Inputs!$C$37,IF(32=Inputs!$C$11+2,0,"")) | P42: =IF(32<=Inputs!$C$11+2,N42-L42,"") | R42: =IF(32<=Inputs!$C$11,"Net interest margin",IF(32=Inputs!$C$11+1,"Net exit fee",IF(32=Inputs!$C$11+2,"Redemption in / senior repaid",""))) | S42: =IF(32<=Inputs!$C$11+2,L42,"") | T42: =IF(32<=Inputs!$C$11,F42-M42,IF(32<=Inputs!$C$11+2,0,"")) | U42: =IF(32<=Inputs!$C$11+2,G42,"") | V42: =IF(32<=Inputs!$C$11+1,Inputs!$C$38,IF(32=Inputs!$C$11+2,0,"")) | W42: =IF(32<=Inputs!$C$11+2,U42-S42,"") | X42: =IF(32<=Inputs!$C$11,IF(OR(Inputs!$C$23="",Inputs!$C$22=""),0,MAX(0,EDATE(Inputs!$C$10,32)-MAX(EDATE(Inputs!$C$10,31),Inputs!$C$23))),"") | Z42: =EDATE(Inputs!$C$10,36) -> 47331 | AA42: =IF(36<=Inputs!$C$11,IF(Inputs!$C$24="Serviced Monthly",F46,0)+IF(36=Inputs!$C$11,Inputs!$C$14+Inputs!$D$17,0),0) -> 0 | AB42: =AA42-IF(36<=Inputs!$C$11,M46,0)-IF(36=Inputs!$C$11,Inputs!$C$37+Inputs!$D$36,0) -> 0
A43: =IF(33<=Inputs!$C$11,33,"") | B43: =IF(33<=Inputs!$C$11,EDATE(Inputs!$C$10,33),IF(33<=Inputs!$C$11+2,EDATE(Inputs!$C$10,Inputs!$C$11),"")) | C43: =IF(33<=Inputs!$C$11,IF(AND(N(X43)>0,N(X43)<D43),"Interest (rate change)","Interest"),IF(33=Inputs!$C$11+1,"Exit fee ("&TEXT(Inputs!$C$17,"0.00%")&")",IF(33=Inputs!$C$11+2,"Redemption – principal repaid",""))) | D43: =IF(33<=Inputs!$C$11,EDATE(Inputs!$C$10,33)-EDATE(Inputs!$C$10,32),"") | E43: =IF(33<=Inputs!$C$11+2,0,"") | F43: =IF(33<=Inputs!$C$11,Inputs!$C$14*(Inputs!$C$21*(D43-X43)+IF(Inputs!$C$22="",Inputs!$C$21,Inputs!$C$22)*X43)/365,IF(33<=Inputs!$C$11+2,0,"")) | G43: =IF(33<=Inputs!$C$11,IF(Inputs!$C$24="Serviced Monthly",F43,0),IF(33=Inputs!$C$11+1,Inputs!$D$17,IF(33=Inputs!$C$11+2,Inputs!$C$14,""))) | H43: =IF(33<=Inputs!$C$11+1,Inputs!$C$14,IF(33=Inputs!$C$11+2,0,"")) | I43: =IF(33<=Inputs!$C$11+2,G43,"") | K43: =IF(Inputs!$C$37=0,"",IF(33<=Inputs!$C$11,"Senior interest",IF(33=Inputs!$C$11+1,"Senior exit fee ("&TEXT(Inputs!$C$36,"0.00%")&")",IF(33=Inputs!$C$11+2,"Senior loan repaid","")))) | L43: =IF(33<=Inputs!$C$11,M43,IF(33=Inputs!$C$11+1,Inputs!$D$36,IF(33=Inputs!$C$11+2,Inputs!$C$37,""))) | M43: =IF(33<=Inputs!$C$11,Inputs!$C$37*Inputs!$C$35*D43/365,IF(33<=Inputs!$C$11+2,0,"")) | N43: =IF(33<=Inputs!$C$11+2,0,"") | O43: =IF(33<=Inputs!$C$11+1,Inputs!$C$37,IF(33=Inputs!$C$11+2,0,"")) | P43: =IF(33<=Inputs!$C$11+2,N43-L43,"") | R43: =IF(33<=Inputs!$C$11,"Net interest margin",IF(33=Inputs!$C$11+1,"Net exit fee",IF(33=Inputs!$C$11+2,"Redemption in / senior repaid",""))) | S43: =IF(33<=Inputs!$C$11+2,L43,"") | T43: =IF(33<=Inputs!$C$11,F43-M43,IF(33<=Inputs!$C$11+2,0,"")) | U43: =IF(33<=Inputs!$C$11+2,G43,"") | V43: =IF(33<=Inputs!$C$11+1,Inputs!$C$38,IF(33=Inputs!$C$11+2,0,"")) | W43: =IF(33<=Inputs!$C$11+2,U43-S43,"") | X43: =IF(33<=Inputs!$C$11,IF(OR(Inputs!$C$23="",Inputs!$C$22=""),0,MAX(0,EDATE(Inputs!$C$10,33)-MAX(EDATE(Inputs!$C$10,32),Inputs!$C$23))),"")
A44: =IF(34<=Inputs!$C$11,34,"") | B44: =IF(34<=Inputs!$C$11,EDATE(Inputs!$C$10,34),IF(34<=Inputs!$C$11+2,EDATE(Inputs!$C$10,Inputs!$C$11),"")) | C44: =IF(34<=Inputs!$C$11,IF(AND(N(X44)>0,N(X44)<D44),"Interest (rate change)","Interest"),IF(34=Inputs!$C$11+1,"Exit fee ("&TEXT(Inputs!$C$17,"0.00%")&")",IF(34=Inputs!$C$11+2,"Redemption – principal repaid",""))) | D44: =IF(34<=Inputs!$C$11,EDATE(Inputs!$C$10,34)-EDATE(Inputs!$C$10,33),"") | E44: =IF(34<=Inputs!$C$11+2,0,"") | F44: =IF(34<=Inputs!$C$11,Inputs!$C$14*(Inputs!$C$21*(D44-X44)+IF(Inputs!$C$22="",Inputs!$C$21,Inputs!$C$22)*X44)/365,IF(34<=Inputs!$C$11+2,0,"")) | G44: =IF(34<=Inputs!$C$11,IF(Inputs!$C$24="Serviced Monthly",F44,0),IF(34=Inputs!$C$11+1,Inputs!$D$17,IF(34=Inputs!$C$11+2,Inputs!$C$14,""))) | H44: =IF(34<=Inputs!$C$11+1,Inputs!$C$14,IF(34=Inputs!$C$11+2,0,"")) | I44: =IF(34<=Inputs!$C$11+2,G44,"") | K44: =IF(Inputs!$C$37=0,"",IF(34<=Inputs!$C$11,"Senior interest",IF(34=Inputs!$C$11+1,"Senior exit fee ("&TEXT(Inputs!$C$36,"0.00%")&")",IF(34=Inputs!$C$11+2,"Senior loan repaid","")))) | L44: =IF(34<=Inputs!$C$11,M44,IF(34=Inputs!$C$11+1,Inputs!$D$36,IF(34=Inputs!$C$11+2,Inputs!$C$37,""))) | M44: =IF(34<=Inputs!$C$11,Inputs!$C$37*Inputs!$C$35*D44/365,IF(34<=Inputs!$C$11+2,0,"")) | N44: =IF(34<=Inputs!$C$11+2,0,"") | O44: =IF(34<=Inputs!$C$11+1,Inputs!$C$37,IF(34=Inputs!$C$11+2,0,"")) | P44: =IF(34<=Inputs!$C$11+2,N44-L44,"") | R44: =IF(34<=Inputs!$C$11,"Net interest margin",IF(34=Inputs!$C$11+1,"Net exit fee",IF(34=Inputs!$C$11+2,"Redemption in / senior repaid",""))) | S44: =IF(34<=Inputs!$C$11+2,L44,"") | T44: =IF(34<=Inputs!$C$11,F44-M44,IF(34<=Inputs!$C$11+2,0,"")) | U44: =IF(34<=Inputs!$C$11+2,G44,"") | V44: =IF(34<=Inputs!$C$11+1,Inputs!$C$38,IF(34=Inputs!$C$11+2,0,"")) | W44: =IF(34<=Inputs!$C$11+2,U44-S44,"") | X44: =IF(34<=Inputs!$C$11,IF(OR(Inputs!$C$23="",Inputs!$C$22=""),0,MAX(0,EDATE(Inputs!$C$10,34)-MAX(EDATE(Inputs!$C$10,33),Inputs!$C$23))),"")
A45: =IF(35<=Inputs!$C$11,35,"") | B45: =IF(35<=Inputs!$C$11,EDATE(Inputs!$C$10,35),IF(35<=Inputs!$C$11+2,EDATE(Inputs!$C$10,Inputs!$C$11),"")) | C45: =IF(35<=Inputs!$C$11,IF(AND(N(X45)>0,N(X45)<D45),"Interest (rate change)","Interest"),IF(35=Inputs!$C$11+1,"Exit fee ("&TEXT(Inputs!$C$17,"0.00%")&")",IF(35=Inputs!$C$11+2,"Redemption – principal repaid",""))) | D45: =IF(35<=Inputs!$C$11,EDATE(Inputs!$C$10,35)-EDATE(Inputs!$C$10,34),"") | E45: =IF(35<=Inputs!$C$11+2,0,"") | F45: =IF(35<=Inputs!$C$11,Inputs!$C$14*(Inputs!$C$21*(D45-X45)+IF(Inputs!$C$22="",Inputs!$C$21,Inputs!$C$22)*X45)/365,IF(35<=Inputs!$C$11+2,0,"")) | G45: =IF(35<=Inputs!$C$11,IF(Inputs!$C$24="Serviced Monthly",F45,0),IF(35=Inputs!$C$11+1,Inputs!$D$17,IF(35=Inputs!$C$11+2,Inputs!$C$14,""))) | H45: =IF(35<=Inputs!$C$11+1,Inputs!$C$14,IF(35=Inputs!$C$11+2,0,"")) | I45: =IF(35<=Inputs!$C$11+2,G45,"") | K45: =IF(Inputs!$C$37=0,"",IF(35<=Inputs!$C$11,"Senior interest",IF(35=Inputs!$C$11+1,"Senior exit fee ("&TEXT(Inputs!$C$36,"0.00%")&")",IF(35=Inputs!$C$11+2,"Senior loan repaid","")))) | L45: =IF(35<=Inputs!$C$11,M45,IF(35=Inputs!$C$11+1,Inputs!$D$36,IF(35=Inputs!$C$11+2,Inputs!$C$37,""))) | M45: =IF(35<=Inputs!$C$11,Inputs!$C$37*Inputs!$C$35*D45/365,IF(35<=Inputs!$C$11+2,0,"")) | N45: =IF(35<=Inputs!$C$11+2,0,"") | O45: =IF(35<=Inputs!$C$11+1,Inputs!$C$37,IF(35=Inputs!$C$11+2,0,"")) | P45: =IF(35<=Inputs!$C$11+2,N45-L45,"") | R45: =IF(35<=Inputs!$C$11,"Net interest margin",IF(35=Inputs!$C$11+1,"Net exit fee",IF(35=Inputs!$C$11+2,"Redemption in / senior repaid",""))) | S45: =IF(35<=Inputs!$C$11+2,L45,"") | T45: =IF(35<=Inputs!$C$11,F45-M45,IF(35<=Inputs!$C$11+2,0,"")) | U45: =IF(35<=Inputs!$C$11+2,G45,"") | V45: =IF(35<=Inputs!$C$11+1,Inputs!$C$38,IF(35=Inputs!$C$11+2,0,"")) | W45: =IF(35<=Inputs!$C$11+2,U45-S45,"") | X45: =IF(35<=Inputs!$C$11,IF(OR(Inputs!$C$23="",Inputs!$C$22=""),0,MAX(0,EDATE(Inputs!$C$10,35)-MAX(EDATE(Inputs!$C$10,34),Inputs!$C$23))),"")
A46: =IF(36<=Inputs!$C$11,36,"") | B46: =IF(36<=Inputs!$C$11,EDATE(Inputs!$C$10,36),IF(36<=Inputs!$C$11+2,EDATE(Inputs!$C$10,Inputs!$C$11),"")) | C46: =IF(36<=Inputs!$C$11,IF(AND(N(X46)>0,N(X46)<D46),"Interest (rate change)","Interest"),IF(36=Inputs!$C$11+1,"Exit fee ("&TEXT(Inputs!$C$17,"0.00%")&")",IF(36=Inputs!$C$11+2,"Redemption – principal repaid",""))) | D46: =IF(36<=Inputs!$C$11,EDATE(Inputs!$C$10,36)-EDATE(Inputs!$C$10,35),"") | E46: =IF(36<=Inputs!$C$11+2,0,"") | F46: =IF(36<=Inputs!$C$11,Inputs!$C$14*(Inputs!$C$21*(D46-X46)+IF(Inputs!$C$22="",Inputs!$C$21,Inputs!$C$22)*X46)/365,IF(36<=Inputs!$C$11+2,0,"")) | G46: =IF(36<=Inputs!$C$11,IF(Inputs!$C$24="Serviced Monthly",F46,0),IF(36=Inputs!$C$11+1,Inputs!$D$17,IF(36=Inputs!$C$11+2,Inputs!$C$14,""))) | H46: =IF(36<=Inputs!$C$11+1,Inputs!$C$14,IF(36=Inputs!$C$11+2,0,"")) | I46: =IF(36<=Inputs!$C$11+2,G46,"") | K46: =IF(Inputs!$C$37=0,"",IF(36<=Inputs!$C$11,"Senior interest",IF(36=Inputs!$C$11+1,"Senior exit fee ("&TEXT(Inputs!$C$36,"0.00%")&")",IF(36=Inputs!$C$11+2,"Senior loan repaid","")))) | L46: =IF(36<=Inputs!$C$11,M46,IF(36=Inputs!$C$11+1,Inputs!$D$36,IF(36=Inputs!$C$11+2,Inputs!$C$37,""))) | M46: =IF(36<=Inputs!$C$11,Inputs!$C$37*Inputs!$C$35*D46/365,IF(36<=Inputs!$C$11+2,0,"")) | N46: =IF(36<=Inputs!$C$11+2,0,"") | O46: =IF(36<=Inputs!$C$11+1,Inputs!$C$37,IF(36=Inputs!$C$11+2,0,"")) | P46: =IF(36<=Inputs!$C$11+2,N46-L46,"") | R46: =IF(36<=Inputs!$C$11,"Net interest margin",IF(36=Inputs!$C$11+1,"Net exit fee",IF(36=Inputs!$C$11+2,"Redemption in / senior repaid",""))) | S46: =IF(36<=Inputs!$C$11+2,L46,"") | T46: =IF(36<=Inputs!$C$11,F46-M46,IF(36<=Inputs!$C$11+2,0,"")) | U46: =IF(36<=Inputs!$C$11+2,G46,"") | V46: =IF(36<=Inputs!$C$11+1,Inputs!$C$38,IF(36=Inputs!$C$11+2,0,"")) | W46: =IF(36<=Inputs!$C$11+2,U46-S46,"") | X46: =IF(36<=Inputs!$C$11,IF(OR(Inputs!$C$23="",Inputs!$C$22=""),0,MAX(0,EDATE(Inputs!$C$10,36)-MAX(EDATE(Inputs!$C$10,35),Inputs!$C$23))),"")
A47: =IF(37<=Inputs!$C$11,37,"") | B47: =IF(37<=Inputs!$C$11,EDATE(Inputs!$C$10,37),IF(37<=Inputs!$C$11+2,EDATE(Inputs!$C$10,Inputs!$C$11),"")) | C47: =IF(37<=Inputs!$C$11,IF(AND(N(X47)>0,N(X47)<D47),"Interest (rate change)","Interest"),IF(37=Inputs!$C$11+1,"Exit fee ("&TEXT(Inputs!$C$17,"0.00%")&")",IF(37=Inputs!$C$11+2,"Redemption – principal repaid",""))) | D47: =IF(37<=Inputs!$C$11,EDATE(Inputs!$C$10,37)-EDATE(Inputs!$C$10,36),"") | E47: =IF(37<=Inputs!$C$11+2,0,"") | F47: =IF(37<=Inputs!$C$11,Inputs!$C$14*(Inputs!$C$21*(D47-X47)+IF(Inputs!$C$22="",Inputs!$C$21,Inputs!$C$22)*X47)/365,IF(37<=Inputs!$C$11+2,0,"")) | G47: =IF(37<=Inputs!$C$11,IF(Inputs!$C$24="Serviced Monthly",F47,0),IF(37=Inputs!$C$11+1,Inputs!$D$17,IF(37=Inputs!$C$11+2,Inputs!$C$14,""))) | H47: =IF(37<=Inputs!$C$11+1,Inputs!$C$14,IF(37=Inputs!$C$11+2,0,"")) | I47: =IF(37<=Inputs!$C$11+2,G47,"") | K47: =IF(Inputs!$C$37=0,"",IF(37<=Inputs!$C$11,"Senior interest",IF(37=Inputs!$C$11+1,"Senior exit fee ("&TEXT(Inputs!$C$36,"0.00%")&")",IF(37=Inputs!$C$11+2,"Senior loan repaid","")))) | L47: =IF(37<=Inputs!$C$11,M47,IF(37=Inputs!$C$11+1,Inputs!$D$36,IF(37=Inputs!$C$11+2,Inputs!$C$37,""))) | M47: =IF(37<=Inputs!$C$11,Inputs!$C$37*Inputs!$C$35*D47/365,IF(37<=Inputs!$C$11+2,0,"")) | N47: =IF(37<=Inputs!$C$11+2,0,"") | O47: =IF(37<=Inputs!$C$11+1,Inputs!$C$37,IF(37=Inputs!$C$11+2,0,"")) | P47: =IF(37<=Inputs!$C$11+2,N47-L47,"") | R47: =IF(37<=Inputs!$C$11,"Net interest margin",IF(37=Inputs!$C$11+1,"Net exit fee",IF(37=Inputs!$C$11+2,"Redemption in / senior repaid",""))) | S47: =IF(37<=Inputs!$C$11+2,L47,"") | T47: =IF(37<=Inputs!$C$11,F47-M47,IF(37<=Inputs!$C$11+2,0,"")) | U47: =IF(37<=Inputs!$C$11+2,G47,"") | V47: =IF(37<=Inputs!$C$11+1,Inputs!$C$38,IF(37=Inputs!$C$11+2,0,"")) | W47: =IF(37<=Inputs!$C$11+2,U47-S47,"") | X47: =IF(37<=Inputs!$C$11,IF(OR(Inputs!$C$23="",Inputs!$C$22=""),0,MAX(0,EDATE(Inputs!$C$10,37)-MAX(EDATE(Inputs!$C$10,36),Inputs!$C$23))),"")
A48: =IF(38<=Inputs!$C$11,38,"") | B48: =IF(38<=Inputs!$C$11,EDATE(Inputs!$C$10,38),IF(38<=Inputs!$C$11+2,EDATE(Inputs!$C$10,Inputs!$C$11),"")) | C48: =IF(38<=Inputs!$C$11,IF(AND(N(X48)>0,N(X48)<D48),"Interest (rate change)","Interest"),IF(38=Inputs!$C$11+1,"Exit fee ("&TEXT(Inputs!$C$17,"0.00%")&")",IF(38=Inputs!$C$11+2,"Redemption – principal repaid",""))) | D48: =IF(38<=Inputs!$C$11,EDATE(Inputs!$C$10,38)-EDATE(Inputs!$C$10,37),"") | E48: =IF(38<=Inputs!$C$11+2,0,"") | F48: =IF(38<=Inputs!$C$11,Inputs!$C$14*(Inputs!$C$21*(D48-X48)+IF(Inputs!$C$22="",Inputs!$C$21,Inputs!$C$22)*X48)/365,IF(38<=Inputs!$C$11+2,0,"")) | G48: =IF(38<=Inputs!$C$11,IF(Inputs!$C$24="Serviced Monthly",F48,0),IF(38=Inputs!$C$11+1,Inputs!$D$17,IF(38=Inputs!$C$11+2,Inputs!$C$14,""))) | H48: =IF(38<=Inputs!$C$11+1,Inputs!$C$14,IF(38=Inputs!$C$11+2,0,"")) | I48: =IF(38<=Inputs!$C$11+2,G48,"") | K48: =IF(Inputs!$C$37=0,"",IF(38<=Inputs!$C$11,"Senior interest",IF(38=Inputs!$C$11+1,"Senior exit fee ("&TEXT(Inputs!$C$36,"0.00%")&")",IF(38=Inputs!$C$11+2,"Senior loan repaid","")))) | L48: =IF(38<=Inputs!$C$11,M48,IF(38=Inputs!$C$11+1,Inputs!$D$36,IF(38=Inputs!$C$11+2,Inputs!$C$37,""))) | M48: =IF(38<=Inputs!$C$11,Inputs!$C$37*Inputs!$C$35*D48/365,IF(38<=Inputs!$C$11+2,0,"")) | N48: =IF(38<=Inputs!$C$11+2,0,"") | O48: =IF(38<=Inputs!$C$11+1,Inputs!$C$37,IF(38=Inputs!$C$11+2,0,"")) | P48: =IF(38<=Inputs!$C$11+2,N48-L48,"") | R48: =IF(38<=Inputs!$C$11,"Net interest margin",IF(38=Inputs!$C$11+1,"Net exit fee",IF(38=Inputs!$C$11+2,"Redemption in / senior repaid",""))) | S48: =IF(38<=Inputs!$C$11+2,L48,"") | T48: =IF(38<=Inputs!$C$11,F48-M48,IF(38<=Inputs!$C$11+2,0,"")) | U48: =IF(38<=Inputs!$C$11+2,G48,"") | V48: =IF(38<=Inputs!$C$11+1,Inputs!$C$38,IF(38=Inputs!$C$11+2,0,"")) | W48: =IF(38<=Inputs!$C$11+2,U48-S48,"") | X48: =IF(38<=Inputs!$C$11,IF(OR(Inputs!$C$23="",Inputs!$C$22=""),0,MAX(0,EDATE(Inputs!$C$10,38)-MAX(EDATE(Inputs!$C$10,37),Inputs!$C$23))),"")
B49: TOTAL | E49: =SUM(E6:E48) -> 3700000 | F49: =SUM(F6:F48) -> 611336.3 | G49: =SUM(G6:G48) -> 4385336.3 | I49: =SUM(I6:I48) -> 685336.3 | L49: =SUM(L6:L48) -> 3136225.2 | M49: =SUM(M6:M48) -> 347350.17 | N49: =SUM(N6:N48) -> 2775000 | P49: =SUM(P6:P48) -> -361225.17 | S49: =SUM(S6:S48) -> 6836225.2 | T49: =SUM(T6:T48) -> 263986.13 | U49: =SUM(U6:U48) -> 7160336.3 | W49: =SUM(W6:W48) -> 324111.13
C51: Whole Loan Profit (£) | F51: =I49 -> 685336.3
C52: Whole Loan IRR (unlevered) | F52: =XIRR(AA6:AA42,Z6:Z42) -> 0.09658141
C53: Senior Funding Cost (£) | F53: =-P49 -> 361225.17
C54: REL Net Profit (£) | F54: =W49 -> 324111.13
C55: REL IRR (on net capital) | F55: =XIRR(AB6:AB42,Z6:Z42) -> 0.18881354
C56: REL Equity Multiple | F56: =IFERROR(1+W49/ABS(AB6),"n/a") -> 1.3593748
C58: Whole Loan IRR assumes REL funds 100%; REL IRR is geared on net capital after senior funding.
C59: ="Ledger ties to calc engine: "&IF(AND(ROUND(I49-SUM(AA6:AA42),2)=0,ROUND(W49-SUM(AB6:AB42),2)=0),"OK","MISMATCH – check") -> Ledger ties to calc engine: OK

Sheet Summary & Breakeven
B2: =Inputs!C6&" – DEAL SUMMARY" -> Housing First Group – DEAL SUMMARY
B3: =Inputs!C8&" | "&Inputs!C9&" | "&TEXT(Inputs!C11,"0")&" months | Gross £"&TEXT(Inputs!C14,"#,##0") -> Residential | Bridge | 24 months | Gross £3,700,000
B5: RETURNS
B6: Whole Loan Profit | C6: =Cashflow!F51 -> 685336.3
B7: Whole Loan IRR | C7: =Cashflow!F52 -> 0.09658141
B8: Senior Funding Cost | C8: =Cashflow!F53 -> 361225.17
B9: REL Net Profit | C9: =Cashflow!F54 -> 324111.13
B10: REL IRR (on net capital) | C10: =Cashflow!F55 -> 0.18881354
B11: REL Equity Multiple | C11: =Cashflow!F56 -> 1.3593748
B12: REL Net Capital Deployed | C12: =Inputs!C38 -> 925000
B13: Profit on Capital (undiscounted) | C13: =IFERROR(C9/Inputs!C38,"n/a") -> 0.35039041
B15: FEE BREAKDOWN (£)
C16: Whole Loan | D16: Senior | E16: Net to REL
B17: Arrangement Fee | C17: =Inputs!D15 -> 37000 | D17: =Inputs!D32 -> 13875 | E17: =C17-D17 -> 23125 | F17: Whole-loan AF earned day 1 less senior AF paid
B18: Broker Fee (paid away) | C18: =Inputs!D16 -> 0 | D18: 0 | E18: 0 | F18: Deducted from borrower advance and paid to broker – not REL income
B19: Admin / Other Fee | C19: =Inputs!C18 -> 0 | D19: 0 | E19: =C19 -> 0 | F19: Flat day-1 fee retained by REL
B20: Exit Fee | C20: =Inputs!D17 -> 37000 | D20: =Inputs!D36 -> 0 | E20: =C20-D20 -> 37000 | F20: Earned on gross loan at redemption less senior exit fee paid
B21: Total Fees | C21: =SUM(C17:C20) -> 74000 | D21: =SUM(D17:D20) -> 13875 | E21: =SUM(E17:E20) -> 60125 | F21: Net fees to REL (excludes broker fee)
B23: FUNDING ANALYSIS (source of REL return)
B24: Whole Loan Rate (charged) | C24: =Inputs!C21 -> 0.0825
B25: Senior Rate (paid) | C25: =Inputs!C35 -> 0.0625
B26: Rate Spread Captured | C26: =C24-C25 -> 0.02 | F26: REL earns the whole-loan rate on the senior piece funded at the cheaper senior rate
B27: Senior Leverage (% of whole loan) | C27: =IFERROR(Inputs!C37/Inputs!C14,0) -> 0.75
B28: Implied REL Rate on Junior Piece | C28: =IFERROR((Inputs!C14*Inputs!C21-Inputs!C37*Inputs!C35)/Inputs!C38,"n/a") -> 0.1425 | F28: Geared running yield before fees
B30: CREDIT METRICS & LOAN BREAKEVEN
C31: Whole Loan | D31: Senior
B32: Redemption Amount (gross + exit fee) | C32: =Inputs!C14*(1+Inputs!C17) -> 3737000 | D32: =Inputs!C37*(1+Inputs!C36) -> 2775000 | F32: Breakeven sale proceeds required to repay in full
B33: Day-1 LTV (gross / MV) | C33: =IFERROR(Inputs!C14/Inputs!C41,"n/a") -> 0.59919028 | D33: =IFERROR(Inputs!C37/Inputs!C41,"n/a") -> 0.44939271
B34: Gross LTV incl. Exit Fee | C34: =IFERROR(C32/Inputs!C41,"n/a") -> 0.60518219 | D34: =IFERROR(D32/Inputs!C41,"n/a") -> 0.44939271
B35: 180-Day LTV (redemption / 180d MV) | C35: =IFERROR(C32/Inputs!C42,"n/a") -> 0.85809414 | D35: =IFERROR(D32/Inputs!C42,"n/a") -> 0.63719862 | F35: Cover under a forced-sale valuation
B36: LTPP (gross / purchase price) | C36: =IFERROR(Inputs!C14/Inputs!C43,"n/a") -> 0.88095238 | D36: =IFERROR(Inputs!C37/Inputs!C43,"n/a") -> 0.66071429
B37: Breakeven £ psf | C37: =IF(Inputs!C44>0,C32/Inputs!C44,"n/a") -> n/a | D37: =IF(Inputs!C44>0,D32/Inputs!C44,"n/a") -> n/a | F37: Residential / commercial / mixed
B38: Breakeven per Unit | C38: =IF(Inputs!C45>0,C32/Inputs!C45,"n/a") -> 233562.5 | D38: =IF(Inputs!C45>0,D32/Inputs!C45,"n/a") -> 173437.5 | F38: Multi-unit residential
B39: Breakeven per Bed / Room | C39: =IF(Inputs!C46>0,C32/Inputs!C46,"n/a") -> n/a | D39: =IF(Inputs!C46>0,D32/Inputs!C46,"n/a") -> n/a | F39: Hotels / leisure
B40: Debt Yield (income / loan) | C40: =IF(Inputs!C47>0,Inputs!C47/Inputs!C14,"n/a") -> 0.12471676 | D40: =IF(AND(Inputs!C47>0,Inputs!C37>0),Inputs!C47/Inputs!C37,"n/a") -> 0.16628901 | F40: Income-producing assets / EBITDA debt yield for hotels
B41: MV Cushion to Breakeven | C41: =IFERROR(1-C32/Inputs!C41,"n/a") -> 0.39481781 | D41: =IFERROR(1-D32/Inputs!C42,"n/a") -> 0.36280138 | F41: % the market value can fall before principal + exit fee is at risk
B44: REL Finance Limited · 27 Hill Street, Mayfair, London, W1J 5LP · relfinance.co.uk

Sheet Statement
C2: REL Finance Limited | G2: LOAN STATEMENT
C3: 27 Hill Street, Mayfair, London, W1J 5LP
B5: Statement period: | C5: =TEXT(Inputs!C10,"dd/mm/yyyy")&" to "&TEXT(EDATE(Inputs!C10,Inputs!C11),"dd/mm/yyyy") -> 01/08/2026 to 01/08/2028 | H5: Blue cells = statement inputs
B6: Underlying loan: | C6: =Inputs!C6&" – "&Inputs!C7 -> Housing First Group – TBC
B8: STATEMENT DETAILS | D8: LOAN DETAILS | F8: REPAYMENT BANK DETAILS
B9: Statement Date | C9: 46265 | D9: Completion Date | E9: =Inputs!C10 -> 46235 | F9: Bank | G9: TBC
B10: Statement # | C10: 1 | D10: Gross Loan (£) | E10: =Inputs!C14 -> 3700000 | F10: Account Name | G10: REL Finance Limited
B11: Loan Ref # | C11: TBC | D11: End Redemption Date | E11: =EDATE(Inputs!C10,Inputs!C11) -> 46966 | F11: Account Number | G11: TBC
B12: Borrower Name | C12: Housing First Group Ltd | D12: Term | E12: =(EDATE(Inputs!C10,Inputs!C11)-Inputs!C10)&" Days" -> 731 Days | F12: Sort Code | G12: TBC
B13: Borrower Address | C13: TBC | D13: Interest Rate | E13: =Inputs!C21 -> 0.0825 | F13: IBAN | G13: TBC
D14: New Rate | E14: =IF(Inputs!C22="","–",TEXT(Inputs!C22,"0.00%")&" from "&TEXT(Inputs!C23,"dd/mm/yyyy")) -> –
D15: Arrangement Fee (£) | E15: =Inputs!D15 -> 37000
D16: Broker Fee (£) | E16: =Inputs!D16 -> 0
D17: Admin / Other Fee (£) | E17: =Inputs!C18 -> 0
D18: Exit Fee (£) | E18: =Inputs!D17 -> 37000
B20: STATEMENT SUMMARY
B21: Original principal loan (£) | C21: =Inputs!C14 -> 3700000 | D21: Closing principal loan balance (£) | E21: =IF($C$9>=EDATE(Inputs!C10,Inputs!C11),0,Inputs!C14) -> 3700000 | F21: Complete rows | G21: =COUNTIF($H$28:$H$70,"Complete") -> 5
B22: Total paid out (£) | C22: =SUMIFS(Cashflow!$E$6:$E$48,Cashflow!$B$6:$B$48,"<="&$C$9) -> 3700000 | D22: Fees charged to date (£) | E22: =Inputs!D15+Inputs!D16+Inputs!C18+IF($C$9>=EDATE(Inputs!C10,Inputs!C11),Inputs!D17,0) -> 37000 | F22: Forecast rows | G22: =COUNTIF($H$28:$H$70,"Forecast") -> 26
B23: Total interest accrued (£) | C23: =SUMIFS(Cashflow!$F$6:$F$48,Cashflow!$B$6:$B$48,"<="&$C$9) -> 0 | D23: Total paid in (£) | E23: =SUMIFS(Cashflow!$G$6:$G$48,Cashflow!$B$6:$B$48,"<="&$C$9) -> 37000
B24: Net advance – day 1 (£) | C24: =Inputs!C26 -> 3663000
B27: Date | C27: Details | D27: Paid Out | E27: Interest Accrued | F27: Paid In | G27: Principal Loan Balance | H27: Complete / Forecast
B28: =IF(Cashflow!$C6="","",Cashflow!$B6) -> 46235 | C28: =IF(Cashflow!$C6="","",Cashflow!$C6) -> Drawdown – gross loan advanced | D28: =IF(Cashflow!$C6="","",Cashflow!$E6) -> 3700000 | E28: =IF(Cashflow!$C6="","",Cashflow!$F6) -> 0 | F28: =IF(Cashflow!$C6="","",Cashflow!$G6) -> 0 | G28: =IF(Cashflow!$C6="","",Cashflow!$H6) -> 3700000 | H28: =IF($B28="","",IF($B28<=$C$9,"Complete","Forecast")) -> Complete
B29: =IF(Cashflow!$C7="","",Cashflow!$B7) -> 46235 | C29: =IF(Cashflow!$C7="","",Cashflow!$C7) -> Arrangement fee (1.00%) – deducted at source | D29: =IF(Cashflow!$C7="","",Cashflow!$E7) -> 0 | E29: =IF(Cashflow!$C7="","",Cashflow!$F7) -> 0 | F29: =IF(Cashflow!$C7="","",Cashflow!$G7) -> 37000 | G29: =IF(Cashflow!$C7="","",Cashflow!$H7) -> 3700000 | H29: =IF($B29="","",IF($B29<=$C$9,"Complete","Forecast")) -> Complete
B30: =IF(Cashflow!$C8="","",Cashflow!$B8) -> 46235 | C30: =IF(Cashflow!$C8="","",Cashflow!$C8) -> Broker fee (0.00%) – paid away to broker | D30: =IF(Cashflow!$C8="","",Cashflow!$E8) -> 0 | E30: =IF(Cashflow!$C8="","",Cashflow!$F8) -> 0 | F30: =IF(Cashflow!$C8="","",Cashflow!$G8) -> 0 | G30: =IF(Cashflow!$C8="","",Cashflow!$H8) -> 3700000 | H30: =IF($B30="","",IF($B30<=$C$9,"Complete","Forecast")) -> Complete
B31: =IF(Cashflow!$C9="","",Cashflow!$B9) -> 46235 | C31: =IF(Cashflow!$C9="","",Cashflow!$C9) -> Admin / other fee – deducted at source | D31: =IF(Cashflow!$C9="","",Cashflow!$E9) -> 0 | E31: =IF(Cashflow!$C9="","",Cashflow!$F9) -> 0 | F31: =IF(Cashflow!$C9="","",Cashflow!$G9) -> 0 | G31: =IF(Cashflow!$C9="","",Cashflow!$H9) -> 3700000 | H31: =IF($B31="","",IF($B31<=$C$9,"Complete","Forecast")) -> Complete
B32: =IF(Cashflow!$C10="","",Cashflow!$B10) -> 46235 | C32: =IF(Cashflow!$C10="","",Cashflow!$C10) -> Interest reserve retained | D32: =IF(Cashflow!$C10="","",Cashflow!$E10) -> 0 | E32: =IF(Cashflow!$C10="","",Cashflow!$F10) -> 0 | F32: =IF(Cashflow!$C10="","",Cashflow!$G10) -> 0 | G32: =IF(Cashflow!$C10="","",Cashflow!$H10) -> 3700000 | H32: =IF($B32="","",IF($B32<=$C$9,"Complete","Forecast")) -> Complete
B33: =IF(Cashflow!$C11="","",Cashflow!$B11) -> 46266 | C33: =IF(Cashflow!$C11="","",Cashflow!$C11) -> Interest | D33: =IF(Cashflow!$C11="","",Cashflow!$E11) -> 0 | E33: =IF(Cashflow!$C11="","",Cashflow!$F11) -> 25925.342 | F33: =IF(Cashflow!$C11="","",Cashflow!$G11) -> 25925.342 | G33: =IF(Cashflow!$C11="","",Cashflow!$H11) -> 3700000 | H33: =IF($B33="","",IF($B33<=$C$9,"Complete","Forecast")) -> Forecast
B34: =IF(Cashflow!$C12="","",Cashflow!$B12) -> 46296 | C34: =IF(Cashflow!$C12="","",Cashflow!$C12) -> Interest | D34: =IF(Cashflow!$C12="","",Cashflow!$E12) -> 0 | E34: =IF(Cashflow!$C12="","",Cashflow!$F12) -> 25089.041 | F34: =IF(Cashflow!$C12="","",Cashflow!$G12) -> 25089.041 | G34: =IF(Cashflow!$C12="","",Cashflow!$H12) -> 3700000 | H34: =IF($B34="","",IF($B34<=$C$9,"Complete","Forecast")) -> Forecast
B35: =IF(Cashflow!$C13="","",Cashflow!$B13) -> 46327 | C35: =IF(Cashflow!$C13="","",Cashflow!$C13) -> Interest | D35: =IF(Cashflow!$C13="","",Cashflow!$E13) -> 0 | E35: =IF(Cashflow!$C13="","",Cashflow!$F13) -> 25925.342 | F35: =IF(Cashflow!$C13="","",Cashflow!$G13) -> 25925.342 | G35: =IF(Cashflow!$C13="","",Cashflow!$H13) -> 3700000 | H35: =IF($B35="","",IF($B35<=$C$9,"Complete","Forecast")) -> Forecast
B36: =IF(Cashflow!$C14="","",Cashflow!$B14) -> 46357 | C36: =IF(Cashflow!$C14="","",Cashflow!$C14) -> Interest | D36: =IF(Cashflow!$C14="","",Cashflow!$E14) -> 0 | E36: =IF(Cashflow!$C14="","",Cashflow!$F14) -> 25089.041 | F36: =IF(Cashflow!$C14="","",Cashflow!$G14) -> 25089.041 | G36: =IF(Cashflow!$C14="","",Cashflow!$H14) -> 3700000 | H36: =IF($B36="","",IF($B36<=$C$9,"Complete","Forecast")) -> Forecast
B37: =IF(Cashflow!$C15="","",Cashflow!$B15) -> 46388 | C37: =IF(Cashflow!$C15="","",Cashflow!$C15) -> Interest | D37: =IF(Cashflow!$C15="","",Cashflow!$E15) -> 0 | E37: =IF(Cashflow!$C15="","",Cashflow!$F15) -> 25925.342 | F37: =IF(Cashflow!$C15="","",Cashflow!$G15) -> 25925.342 | G37: =IF(Cashflow!$C15="","",Cashflow!$H15) -> 3700000 | H37: =IF($B37="","",IF($B37<=$C$9,"Complete","Forecast")) -> Forecast
B38: =IF(Cashflow!$C16="","",Cashflow!$B16) -> 46419 | C38: =IF(Cashflow!$C16="","",Cashflow!$C16) -> Interest | D38: =IF(Cashflow!$C16="","",Cashflow!$E16) -> 0 | E38: =IF(Cashflow!$C16="","",Cashflow!$F16) -> 25925.342 | F38: =IF(Cashflow!$C16="","",Cashflow!$G16) -> 25925.342 | G38: =IF(Cashflow!$C16="","",Cashflow!$H16) -> 3700000 | H38: =IF($B38="","",IF($B38<=$C$9,"Complete","Forecast")) -> Forecast
B39: =IF(Cashflow!$C17="","",Cashflow!$B17) -> 46447 | C39: =IF(Cashflow!$C17="","",Cashflow!$C17) -> Interest | D39: =IF(Cashflow!$C17="","",Cashflow!$E17) -> 0 | E39: =IF(Cashflow!$C17="","",Cashflow!$F17) -> 23416.438 | F39: =IF(Cashflow!$C17="","",Cashflow!$G17) -> 23416.438 | G39: =IF(Cashflow!$C17="","",Cashflow!$H17) -> 3700000 | H39: =IF($B39="","",IF($B39<=$C$9,"Complete","Forecast")) -> Forecast
... B70: =IF(Cashflow!$C48="","",Cashflow!$B48) | C70: =IF(Cashflow!$C48="","",Cashflow!$C48) | D70: =IF(Cashflow!$C48="","",Cashflow!$E48) | E70: =IF(Cashflow!$C48="","",Cashflow!$F48) | F70: =IF(Cashflow!$C48="","",Cashflow!$G48) | G70: =IF(Cashflow!$C48="","",Cashflow!$H48) | H70: =IF($B70="","",IF($B70<=$C$9,"Complete","Forecast"))
B71: TOTAL | D71: =SUM(D28:D70) -> 3700000 | E71: =SUM(E28:E70) -> 611336.3 | F71: =SUM(F28:F70) -> 4385336.3
B74: REL Finance Limited · 27 Hill Street, Mayfair, London, W1J 5LP · info@relfinance.co.uk · relfinance.co.uk
B75: Registered in England & Wales, company no. 14285643. Registered with the FCA for AML, firm reference 990924.
